Workbook

Sheet 使用说明
A1: D05｜企业经营健康管理试点运营工具包 V1.0
A2: 版本日期：2026-10-12 · 对应：D01 30天试运营、D02 首批招募、F01 90天Go/No-Go、MVP 试点指标、B08 高级专项验证
A4: 用途 | B4: 试点第一天起记录真实数据：筛客户、记工时、记互动、记支出、做复盘，自动汇总成 KPI 看板。90天后用于 F01 V01–V05 验证报告与 BP V0.4 17.7 主线裁决。
A5: 颜色约定 | B5: 浅黄底 + 蓝字 = 需要填写的单元格；黑字 = 公式，请勿修改；绿字 = 引用“参数”表。
A6: 示例行 | B6: 各表第5行起的灰色斜体是示例（企业编号“示例-01/02”），仅用于演示格式和看板计算，正式使用前清空示例行中浅黄色输入格的内容即可；不要删除整行，以免破坏公式。
A7: 客户筛选 | B7: D02 第十三节：五项优先条件各打 0/1/2 分，有慎重项时提示顾问人工判断。阈值在“参数”表修改。
A8: 客户台账 | B8: 每家企业一行，编号唯一（建议 HY-001 会员线、ZX-001 专项线）。状态、产品下拉选择。会员线填开始日后自动算出30天结束日。
A9: 工时记录 | B9: 每做完一件事记一行。只填“手填人工分钟”最快；也可填开始/结束时间自动计算。工作类型决定工时性质（一次性/维护/专项/共享/非服务）和预算类别。共享任务企业编号填“共享”，开发、协会等填“内部”。AI 运行时间单独填，不算人工。
A10: 互动记录 | B10: 老板主动提问、发数据、周报发送结果（未修改/修改后/退回）、建议被采用、增值线索、转介绍、发错对象、数字错误，逐条记录。
A11: 支出记录 | B11: 按实际账单记录；固定订阅不按客户重复分摊，只有确实因某家企业新增的支出才标“增量”并填企业编号。
A12: 30天复盘 | B12: 体验结束时与老板沟通填写，A–D 四项为顾问按 D01 第十一章的内部判断。
A13: KPI看板 | B13: 一、总体指标与目标对比（目标值来自 MVP / F01 / B08，在“参数”表可改）；二、按月工时与 132 小时时间预算对比；三、分企业明细，逐行对应客户台账第5–54行。
A14: 容量 | B14: 客户台账 50 行、工时与互动记录各 1000 行、支出 500 行。超出时把最后一行（含公式）向下复制即可；KPI 看板公式范围需同步扩大。
A15: 口径提醒 | B15: 样本很小，任何单一指标都不能单独作为 GO/NO-GO 依据（F01 第八章）。口头意向不算成交，只认实际收款。

Sheet KPI看板
A1: 试点 KPI 看板
A2: 全部为公式，勿手改（看板日期除外）。删除各表示例行后即为真实数据。目标值在“参数”表修改。
A3: 看板日期 | B3: =TODAY() | C3: ← 默认今天，可改为某个复盘日
A5: 一、总体指标 | G5: 二、月度工时 vs 时间预算（小时）
A6: 指标 | B6: 当前值 | C6: 目标 | D6: 达标？ | E6: 口径 | G6: 月份起始日 | H6: 客户服务 | I6: 客户开发与销售 | J6: 产品及AI工作流 | K6: 一般运营管理 | L6: 协会公益共建 | M6: 合计 | N6: 客户服务占用率
A7: 体验企业数（家） | B7: =COUNTIFS(客户台账!$D$5:$D$54,"会员线",客户台账!$K$5:$K$54,"<>") | C7: =参数!$B$31 | D7: =IF(B7="","",IF(B7>=C7,"✓","✗")) | E7: 会员线中已填开始日的企业 | G7: 月度预算 | H7: =参数!$F$5 | I7: =参数!$F$6 | J7: =参数!$F$7 | K7: =参数!$F$8 | L7: =参数!$F$9 | M7: =SUM(H7:L7)
A8: 正式转正企业数（家） | B8: =COUNTIFS(客户台账!$D$5:$D$54,"会员线",客户台账!$I$5:$I$54,"正式会员") | C8: =参数!$B$32 | D8: =IF(B8="","",IF(B8>=C8,"✓","✗")) | E8: 会员线状态=正式会员 | G8: 46296 | H8: =SUMIFS(工时记录!$I$5:$I$1004,工时记录!$L$5:$L$1004,"客户服务",工时记录!$A$5:$A$1004,">="&$G8,工时记录!$A$5:$A$1004,"<"&EDATE($G8,1))/60 | I8: =SUMIFS(工时记录!$I$5:$I$1004,工时记录!$L$5:$L$1004,"客户开发与销售",工时记录!$A$5:$A$1004,">="&$G8,工时记录!$A$5:$A$1004,"<"&EDATE($G8,1))/60 | J8: =SUMIFS(工时记录!$I$5:$I$1004,工时记录!$L$5:$L$1004,"产品及AI工作流",工时记录!$A$5:$A$1004,">="&$G8,工时记录!$A$5:$A$1004,"<"&EDATE($G8,1))/60 | K8: =SUMIFS(工时记录!$I$5:$I$1004,工时记录!$L$5:$L$1004,"一般运营管理",工时记录!$A$5:$A$1004,">="&$G8,工时记录!$A$5:$A$1004,"<"&EDATE($G8,1))/60 | L8: =SUMIFS(工时记录!$I$5:$I$1004,工时记录!$L$5:$L$1004,"协会公益共建",工时记录!$A$5:$A$1004,">="&$G8,工时记录!$A$5:$A$1004,"<"&EDATE($G8,1))/60 | M8: =SUM(H8:L8) | N8: =IF($H$7=0,"",H8/$H$7)
A9: 体验→转正率 | B9: =IF(B7=0,"",B8/B7) | E9: 转正数 ÷ 体验数；样本小，仅作参考 | G9: 46327 | H9: =SUMIFS(工时记录!$I$5:$I$1004,工时记录!$L$5:$L$1004,"客户服务",工时记录!$A$5:$A$1004,">="&$G9,工时记录!$A$5:$A$1004,"<"&EDATE($G9,1))/60 | I9: =SUMIFS(工时记录!$I$5:$I$1004,工时记录!$L$5:$L$1004,"客户开发与销售",工时记录!$A$5:$A$1004,">="&$G9,工时记录!$A$5:$A$1004,"<"&EDATE($G9,1))/60 | J9: =SUMIFS(工时记录!$I$5:$I$1004,工时记录!$L$5:$L$1004,"产品及AI工作流",工时记录!$A$5:$A$1004,">="&$G9,工时记录!$A$5:$A$1004,"<"&EDATE($G9,1))/60 | K9: =SUMIFS(工时记录!$I$5:$I$1004,工时记录!$L$5:$L$1004,"一般运营管理",工时记录!$A$5:$A$1004,">="&$G9,工时记录!$A$5:$A$1004,"<"&EDATE($G9,1))/60 | L9: =SUMIFS(工时记录!$I$5:$I$1004,工时记录!$L$5:$L$1004,"协会公益共建",工时记录!$A$5:$A$1004,">="&$G9,工时记录!$A$5:$A$1004,"<"&EDATE($G9,1))/60 | M9: =SUM(H9:L9) | N9: =IF($H$7=0,"",H9/$H$7)
A10: 数据按时发送率（企业平均） | B10: =IFERROR(AVERAGE($L$30:$L$79),"") | C10: =参数!$B$33 | D10: =IF(B10="","",IF(B10>=C10,"✓","✗")) | E10: 每家：老板发送数据次数 ÷ 已服务周数（封顶100%），再取平均 | G10: 46357 | H10: =SUMIFS(工时记录!$I$5:$I$1004,工时记录!$L$5:$L$1004,"客户服务",工时记录!$A$5:$A$1004,">="&$G10,工时记录!$A$5:$A$1004,"<"&EDATE($G10,1))/60 | I10: =SUMIFS(工时记录!$I$5:$I$1004,工时记录!$L$5:$L$1004,"客户开发与销售",工时记录!$A$5:$A$1004,">="&$G10,工时记录!$A$5:$A$1004,"<"&EDATE($G10,1))/60 | J10: =SUMIFS(工时记录!$I$5:$I$1004,工时记录!$L$5:$L$1004,"产品及AI工作流",工时记录!$A$5:$A$1004,">="&$G10,工时记录!$A$5:$A$1004,"<"&EDATE($G10,1))/60 | K10: =SUMIFS(工时记录!$I$5:$I$1004,工时记录!$L$5:$L$1004,"一般运营管理",工时记录!$A$5:$A$1004,">="&$G10,工时记录!$A$5:$A$1004,"<"&EDATE($G10,1))/60 | L10: =SUMIFS(工时记录!$I$5:$I$1004,工时记录!$L$5:$L$1004,"协会公益共建",工时记录!$A$5:$A$1004,">="&$G10,工时记录!$A$5:$A$1004,"<"&EDATE($G10,1))/60 | M10: =SUM(H10:L10) | N10: =IF($H$7=0,"",H10/$H$7)
A11: 周报修改率 | B11: =IFERROR((COUNTIF(互动记录!$C$5:$C$1004,"周报经修改后发送")+COUNTIF(互动记录!$C$5:$C$1004,"周报退回重做"))/(COUNTIF(互动记录!$C$5:$C$1004,"周报已发送（未修改）")+COUNTIF(互动记录!$C$5:$C$1004,"周报经修改后发送")+COUNTIF(互动记录!$C$5:$C$1004,"周报退回重做")),"") | C11: =参数!$B$34 | D11: =IF(B11="","",IF(B11<=C11,"✓","✗")) | E11: (修改后发送 + 退回重做) ÷ 全部周报；目标针对第4周 | G11: 46388 | H11: =SUMIFS(工时记录!$I$5:$I$1004,工时记录!$L$5:$L$1004,"客户服务",工时记录!$A$5:$A$1004,">="&$G11,工时记录!$A$5:$A$1004,"<"&EDATE($G11,1))/60 | I11: =SUMIFS(工时记录!$I$5:$I$1004,工时记录!$L$5:$L$1004,"客户开发与销售",工时记录!$A$5:$A$1004,">="&$G11,工时记录!$A$5:$A$1004,"<"&EDATE($G11,1))/60 | J11: =SUMIFS(工时记录!$I$5:$I$1004,工时记录!$L$5:$L$1004,"产品及AI工作流",工时记录!$A$5:$A$1004,">="&$G11,工时记录!$A$5:$A$1004,"<"&EDATE($G11,1))/60 | K11: =SUMIFS(工时记录!$I$5:$I$1004,工时记录!$L$5:$L$1004,"一般运营管理",工时记录!$A$5:$A$1004,">="&$G11,工时记录!$A$5:$A$1004,"<"&EDATE($G11,1))/60 | L11: =SUMIFS(工时记录!$I$5:$I$1004,工时记录!$L$5:$L$1004,"协会公益共建",工时记录!$A$5:$A$1004,">="&$G11,工时记录!$A$5:$A$1004,"<"&EDATE($G11,1))/60 | M11: =SUM(H11:L11) | N11: =IF($H$7=0,"",H11/$H$7)
A12: 每企业每周维护人工（分钟） | B12: =IFERROR(AVERAGE($J$30:$J$79),"") | C12: =参数!$B$35 | D12: =IF(B12="","",IF(B12<=C12,"✓","✗")) | E12: 工时性质=维护 的分钟 ÷ 已服务周数，取平均；不含首次建档 | G12: 客户服务月度占用超过约80%（≈52小时，F02 常规排期参考线）时，新专项顺延开工（BP V0.4 17.6）。
A13: 发错对象（次） | B13: =COUNTIF(互动记录!$C$5:$C$1004,"发错对象") | C13: =参数!$B$36 | D13: =IF(B13="","",IF(B13<=C13,"✓","✗")) | E13: 任何一次都需复盘
A14: 数字错误（次） | B14: =COUNTIF(互动记录!$C$5:$C$1004,"数字错误") | E14: 已发出内容中被发现的数字错误
A15: 主动提问/提需求企业数（家） | B15: =COUNTIF($M$30:$M$79,">0") | C15: =参数!$B$37 | D15: =IF(B15="","",IF(B15>=C15,"✓","✗")) | E15: 至少有1次老板主动提问/提需求的企业
A16: 增值/专项线索（条） | B16: =COUNTIF(互动记录!$C$5:$C$1004,"增值/专项线索") | E16: 来自互动记录
A17: 专项正式报价数 | B17: =COUNTIFS(客户台账!$D$5:$D$54,"专项线",客户台账!$I$5:$I$54,"已报价（专项）")+COUNTIFS(客户台账!$D$5:$D$54,"专项线",客户台账!$I$5:$I$54,"已签约（专项）")+COUNTIFS(客户台账!$D$5:$D$54,"专项线",客户台账!$I$5:$I$54,"交付中（专项）")+COUNTIFS(客户台账!$D$5:$D$54,"专项线",客户台账!$I$5:$I$54,"已验收（专项）") | C17: =参数!$B$38 | D17: =IF(B17="","",IF(B17>=C17,"✓","✗")) | E17: 状态已到报价及之后的专项客户
A18: 专项成交数 | B18: =COUNTIFS(客户台账!$D$5:$D$54,"专项线",客户台账!$I$5:$I$54,"已签约（专项）")+COUNTIFS(客户台账!$D$5:$D$54,"专项线",客户台账!$I$5:$I$54,"交付中（专项）")+COUNTIFS(客户台账!$D$5:$D$54,"专项线",客户台账!$I$5:$I$54,"已验收（专项）") | C18: =参数!$B$39 | D18: =IF(B18="","",IF(B18>=C18,"✓","✗")) | E18: 已签约、交付中、已验收
A19: 累计实收：会员线（元） | B19: =SUMIFS(客户台账!$N$5:$N$54,客户台账!$D$5:$D$54,"会员线") | E19: 客户台账 累计实收
A20: 累计实收：专项线（元） | B20: =SUMIFS(客户台账!$N$5:$N$54,客户台账!$D$5:$D$54,"专项线") | E20: 客户台账 累计实收
A21: 累计现金支出（元） | B21: =SUM(支出记录!$E$5:$E$504) | E21: 固定 + 增量
A22: 项目现金结余（元） | B22: =B19+B20-B21 | E22: F01 10.5 结果一：实际收入 − 实际现金支出
A23: 每小时现金贡献：会员线（元/时） | B23: =IFERROR(B19/(SUMIFS(工时记录!$I$5:$I$1004,工时记录!$C$5:$C$1004,"会员线")/60),"") | E23: 会员线实收 ÷ 会员线全部人工工时（含获客）
A24: 每小时现金贡献：专项线（元/时） | B24: =IFERROR(B20/(SUMIFS(工时记录!$I$5:$I$1004,工时记录!$C$5:$C$1004,"专项线")/60),"") | E24: 专项线实收 ÷ 专项线全部人工工时（含售前）；用于 BP V0.4 17.7 主线裁决
A28: 三、分企业明细（逐行对应客户台账第5–54行）
A29: 企业编号 | B29: 企业简称 | C29: 线别 | D29: 当前状态 | E29: 已服务周数 | F29: 一次性工时(时) | G29: 维护工时(时) | H29: 专项工时(时) | I29: 合计工时(时) | J29: 每周维护人工(分钟) | K29: 数据发送次数 | L29: 数据按时率 | M29: 主动提问次数 | N29: 周报发送数 | O29: 周报修改率 | P29: 建议被采用次数 | Q29: 增值线索 | R29: 实收(元) | S29: 增量支出(元) | T29: 每小时现金贡献(元/时)
A30: =IF(客户台账!A5="","",客户台账!A5) | B30: =IF($A30="","",客户台账!B5) | C30: =IF($A30="","",客户台账!D5) | D30: =IF($A30="","",客户台账!I5) | E30: =IF(OR($A30="",客户台账!K5="",C30<>"会员线"),"",MAX(1,ROUNDUP((MIN(客户台账!L5,$B$3)-客户台账!K5+1)/7,0))) | F30: =IF($A30="","",SUMIFS(工时记录!$I$5:$I$1004,工时记录!$B$5:$B$1004,$A30,工时记录!$K$5:$K$1004,"一次性")/60) | G30: =IF($A30="","",SUMIFS(工时记录!$I$5:$I$1004,工时记录!$B$5:$B$1004,$A30,工时记录!$K$5:$K$1004,"维护")/60) | H30: =IF($A30="","",SUMIFS(工时记录!$I$5:$I$1004,工时记录!$B$5:$B$1004,$A30,工时记录!$K$5:$K$1004,"专项")/60) | I30: =IF($A30="","",SUMIFS(工时记录!$I$5:$I$1004,工时记录!$B$5:$B$1004,$A30)/60) | J30: =IF(OR($A30="",E30=""),"",G30*60/E30) | K30: =IF($A30="","",COUNTIFS(互动记录!$B$5:$B$1004,$A30,互动记录!$C$5:$C$1004,"老板发送数据")) | L30: =IF(OR($A30="",E30=""),"",MIN(1,K30/E30)) | M30: =IF($A30="","",COUNTIFS(互动记录!$B$5:$B$1004,$A30,互动记录!$C$5:$C$1004,"老板主动提问/提需求")) | N30: =IF($A30="","",COUNTIFS(互动记录!$B$5:$B$1004,$A30,互动记录!$C$5:$C$1004,"周报已发送（未修改）")+COUNTIFS(互动记录!$B$5:$B$1004,$A30,互动记录!$C$5:$C$1004,"周报经修改后发送")+COUNTIFS(互动记录!$B$5:$B$1004,$A30,互动记录!$C$5:$C$1004,"周报退回重做")) | O30: =IF(OR($A30="",N30=0),"",(COUNTIFS(互动记录!$B$5:$B$1004,$A30,互动记录!$C$5:$C$1004,"周报经修改后发送")+COUNTIFS(互动记录!$B$5:$B$1004,$A30,互动记录!$C$5:$C$1004,"周报退回重做"))/N30) | P30: =IF($A30="","",COUNTIFS(互动记录!$B$5:$B$1004,$A30,互动记录!$C$5:$C$1004,"建议被采用")) | Q30: =IF($A30="","",COUNTIFS(互动记录!$B$5:$B$1004,$A30,互动记录!$C$5:$C$1004,"增值/专项线索")) | R30: =IF($A30="","",客户台账!N5) | S30: =IF($A30="","",SUMIFS(支出记录!$E$5:$E$504,支出记录!$D$5:$D$504,$A30)) | T30: =IF(OR($A30="",I30=0),"",(R30-S30)/I30)
A31: =IF(客户台账!A6="","",客户台账!A6) | B31: =IF($A31="","",客户台账!B6) | C31: =IF($A31="","",客户台账!D6) | D31: =IF($A31="","",客户台账!I6) | E31: =IF(OR($A31="",客户台账!K6="",C31<>"会员线"),"",MAX(1,ROUNDUP((MIN(客户台账!L6,$B$3)-客户台账!K6+1)/7,0))) | F31: =IF($A31="","",SUMIFS(工时记录!$I$5:$I$1004,工时记录!$B$5:$B$1004,$A31,工时记录!$K$5:$K$1004,"一次性")/60) | G31: =IF($A31="","",SUMIFS(工时记录!$I$5:$I$1004,工时记录!$B$5:$B$1004,$A31,工时记录!$K$5:$K$1004,"维护")/60) | H31: =IF($A31="","",SUMIFS(工时记录!$I$5:$I$1004,工时记录!$B$5:$B$1004,$A31,工时记录!$K$5:$K$1004,"专项")/60) | I31: =IF($A31="","",SUMIFS(工时记录!$I$5:$I$1004,工时记录!$B$5:$B$1004,$A31)/60) | J31: =IF(OR($A31="",E31=""),"",G31*60/E31) | K31: =IF($A31="","",COUNTIFS(互动记录!$B$5:$B$1004,$A31,互动记录!$C$5:$C$1004,"老板发送数据")) | L31: =IF(OR($A31="",E31=""),"",MIN(1,K31/E31)) | M31: =IF($A31="","",COUNTIFS(互动记录!$B$5:$B$1004,$A31,互动记录!$C$5:$C$1004,"老板主动提问/提需求")) | N31: =IF($A31="","",COUNTIFS(互动记录!$B$5:$B$1004,$A31,互动记录!$C$5:$C$1004,"周报已发送（未修改）")+COUNTIFS(互动记录!$B$5:$B$1004,$A31,互动记录!$C$5:$C$1004,"周报经修改后发送")+COUNTIFS(互动记录!$B$5:$B$1004,$A31,互动记录!$C$5:$C$1004,"周报退回重做")) | O31: =IF(OR($A31="",N31=0),"",(COUNTIFS(互动记录!$B$5:$B$1004,$A31,互动记录!$C$5:$C$1004,"周报经修改后发送")+COUNTIFS(互动记录!$B$5:$B$1004,$A31,互动记录!$C$5:$C$1004,"周报退回重做"))/N31) | P31: =IF($A31="","",COUNTIFS(互动记录!$B$5:$B$1004,$A31,互动记录!$C$5:$C$1004,"建议被采用")) | Q31: =IF($A31="","",COUNTIFS(互动记录!$B$5:$B$1004,$A31,互动记录!$C$5:$C$1004,"增值/专项线索")) | R31: =IF($A31="","",客户台账!N6) | S31: =IF($A31="","",SUMIFS(支出记录!$E$5:$E$504,支出记录!$D$5:$D$504,$A31)) | T31: =IF(OR($A31="",I31=0),"",(R31-S31)/I31)
A32: =IF(客户台账!A7="","",客户台账!A7) | B32: =IF($A32="","",客户台账!B7) | C32: =IF($A32="","",客户台账!D7) | D32: =IF($A32="","",客户台账!I7) | E32: =IF(OR($A32="",客户台账!K7="",C32<>"会员线"),"",MAX(1,ROUNDUP((MIN(客户台账!L7,$B$3)-客户台账!K7+1)/7,0))) | F32: =IF($A32="","",SUMIFS(工时记录!$I$5:$I$1004,工时记录!$B$5:$B$1004,$A32,工时记录!$K$5:$K$1004,"一次性")/60) | G32: =IF($A32="","",SUMIFS(工时记录!$I$5:$I$1004,工时记录!$B$5:$B$1004,$A32,工时记录!$K$5:$K$1004,"维护")/60) | H32: =IF($A32="","",SUMIFS(工时记录!$I$5:$I$1004,工时记录!$B$5:$B$1004,$A32,工时记录!$K$5:$K$1004,"专项")/60) | I32: =IF($A32="","",SUMIFS(工时记录!$I$5:$I$1004,工时记录!$B$5:$B$1004,$A32)/60) | J32: =IF(OR($A32="",E32=""),"",G32*60/E32) | K32: =IF($A32="","",COUNTIFS(互动记录!$B$5:$B$1004,$A32,互动记录!$C$5:$C$1004,"老板发送数据")) | L32: =IF(OR($A32="",E32=""),"",MIN(1,K32/E32)) | M32: =IF($A32="","",COUNTIFS(互动记录!$B$5:$B$1004,$A32,互动记录!$C$5:$C$1004,"老板主动提问/提需求")) | N32: =IF($A32="","",COUNTIFS(互动记录!$B$5:$B$1004,$A32,互动记录!$C$5:$C$1004,"周报已发送（未修改）")+COUNTIFS(互动记录!$B$5:$B$1004,$A32,互动记录!$C$5:$C$1004,"周报经修改后发送")+COUNTIFS(互动记录!$B$5:$B$1004,$A32,互动记录!$C$5:$C$1004,"周报退回重做")) | O32: =IF(OR($A32="",N32=0),"",(COUNTIFS(互动记录!$B$5:$B$1004,$A32,互动记录!$C$5:$C$1004,"周报经修改后发送")+COUNTIFS(互动记录!$B$5:$B$1004,$A32,互动记录!$C$5:$C$1004,"周报退回重做"))/N32) | P32: =IF($A32="","",COUNTIFS(互动记录!$B$5:$B$1004,$A32,互动记录!$C$5:$C$1004,"建议被采用")) | Q32: =IF($A32="","",COUNTIFS(互动记录!$B$5:$B$1004,$A32,互动记录!$C$5:$C$1004,"增值/专项线索")) | R32: =IF($A32="","",客户台账!N7) | S32: =IF($A32="","",SUMIFS(支出记录!$E$5:$E$504,支出记录!$D$5:$D$504,$A32)) | T32: =IF(OR($A32="",I32=0),"",(R32-S32)/I32)
A33: =IF(客户台账!A8="","",客户台账!A8) | B33: =IF($A33="","",客户台账!B8) | C33: =IF($A33="","",客户台账!D8) | D33: =IF($A33="","",客户台账!I8) | E33: =IF(OR($A33="",客户台账!K8="",C33<>"会员线"),"",MAX(1,ROUNDUP((MIN(客户台账!L8,$B$3)-客户台账!K8+1)/7,0))) | F33: =IF($A33="","",SUMIFS(工时记录!$I$5:$I$1004,工时记录!$B$5:$B$1004,$A33,工时记录!$K$5:$K$1004,"一次性")/60) | G33: =IF($A33="","",SUMIFS(工时记录!$I$5:$I$1004,工时记录!$B$5:$B$1004,$A33,工时记录!$K$5:$K$1004,"维护")/60) | H33: =IF($A33="","",SUMIFS(工时记录!$I$5:$I$1004,工时记录!$B$5:$B$1004,$A33,工时记录!$K$5:$K$1004,"专项")/60) | I33: =IF($A33="","",SUMIFS(工时记录!$I$5:$I$1004,工时记录!$B$5:$B$1004,$A33)/60) | J33: =IF(OR($A33="",E33=""),"",G33*60/E33) | K33: =IF($A33="","",COUNTIFS(互动记录!$B$5:$B$1004,$A33,互动记录!$C$5:$C$1004,"老板发送数据")) | L33: =IF(OR($A33="",E33=""),"",MIN(1,K33/E33)) | M33: =IF($A33="","",COUNTIFS(互动记录!$B$5:$B$1004,$A33,互动记录!$C$5:$C$1004,"老板主动提问/提需求")) | N33: =IF($A33="","",COUNTIFS(互动记录!$B$5:$B$1004,$A33,互动记录!$C$5:$C$1004,"周报已发送（未修改）")+COUNTIFS(互动记录!$B$5:$B$1004,$A33,互动记录!$C$5:$C$1004,"周报经修改后发送")+COUNTIFS(互动记录!$B$5:$B$1004,$A33,互动记录!$C$5:$C$1004,"周报退回重做")) | O33: =IF(OR($A33="",N33=0),"",(COUNTIFS(互动记录!$B$5:$B$1004,$A33,互动记录!$C$5:$C$1004,"周报经修改后发送")+COUNTIFS(互动记录!$B$5:$B$1004,$A33,互动记录!$C$5:$C$1004,"周报退回重做"))/N33) | P33: =IF($A33="","",COUNTIFS(互动记录!$B$5:$B$1004,$A33,互动记录!$C$5:$C$1004,"建议被采用")) | Q33: =IF($A33="","",COUNTIFS(互动记录!$B$5:$B$1004,$A33,互动记录!$C$5:$C$1004,"增值/专项线索")) | R33: =IF($A33="","",客户台账!N8) | S33: =IF($A33="","",SUMIFS(支出记录!$E$5:$E$504,支出记录!$D$5:$D$504,$A33)) | T33: =IF(OR($A33="",I33=0),"",(R33-S33)/I33)
A34: =IF(客户台账!A9="","",客户台账!A9) | B34: =IF($A34="","",客户台账!B9) | C34: =IF($A34="","",客户台账!D9) | D34: =IF($A34="","",客户台账!I9) | E34: =IF(OR($A34="",客户台账!K9="",C34<>"会员线"),"",MAX(1,ROUNDUP((MIN(客户台账!L9,$B$3)-客户台账!K9+1)/7,0))) | F34: =IF($A34="","",SUMIFS(工时记录!$I$5:$I$1004,工时记录!$B$5:$B$1004,$A34,工时记录!$K$5:$K$1004,"一次性")/60) | G34: =IF($A34="","",SUMIFS(工时记录!$I$5:$I$1004,工时记录!$B$5:$B$1004,$A34,工时记录!$K$5:$K$1004,"维护")/60) | H34: =IF($A34="","",SUMIFS(工时记录!$I$5:$I$1004,工时记录!$B$5:$B$1004,$A34,工时记录!$K$5:$K$1004,"专项")/60) | I34: =IF($A34="","",SUMIFS(工时记录!$I$5:$I$1004,工时记录!$B$5:$B$1004,$A34)/60) | J34: =IF(OR($A34="",E34=""),"",G34*60/E34) | K34: =IF($A34="","",COUNTIFS(互动记录!$B$5:$B$1004,$A34,互动记录!$C$5:$C$1004,"老板发送数据")) | L34: =IF(OR($A34="",E34=""),"",MIN(1,K34/E34)) | M34: =IF($A34="","",COUNTIFS(互动记录!$B$5:$B$1004,$A34,互动记录!$C$5:$C$1004,"老板主动提问/提需求")) | N34: =IF($A34="","",COUNTIFS(互动记录!$B$5:$B$1004,$A34,互动记录!$C$5:$C$1004,"周报已发送（未修改）")+COUNTIFS(互动记录!$B$5:$B$1004,$A34,互动记录!$C$5:$C$1004,"周报经修改后发送")+COUNTIFS(互动记录!$B$5:$B$1004,$A34,互动记录!$C$5:$C$1004,"周报退回重做")) | O34: =IF(OR($A34="",N34=0),"",(COUNTIFS(互动记录!$B$5:$B$1004,$A34,互动记录!$C$5:$C$1004,"周报经修改后发送")+COUNTIFS(互动记录!$B$5:$B$1004,$A34,互动记录!$C$5:$C$1004,"周报退回重做"))/N34) | P34: =IF($A34="","",COUNTIFS(互动记录!$B$5:$B$1004,$A34,互动记录!$C$5:$C$1004,"建议被采用")) | Q34: =IF($A34="","",COUNTIFS(互动记录!$B$5:$B$1004,$A34,互动记录!$C$5:$C$1004,"增值/专项线索")) | R34: =IF($A34="","",客户台账!N9) | S34: =IF($A34="","",SUMIFS(支出记录!$E$5:$E$504,支出记录!$D$5:$D$504,$A34)) | T34: =IF(OR($A34="",I34=0),"",(R34-S34)/I34)
A35: =IF(客户台账!A10="","",客户台账!A10) | B35: =IF($A35="","",客户台账!B10) | C35: =IF($A35="","",客户台账!D10) | D35: =IF($A35="","",客户台账!I10) | E35: =IF(OR($A35="",客户台账!K10="",C35<>"会员线"),"",MAX(1,ROUNDUP((MIN(客户台账!L10,$B$3)-客户台账!K10+1)/7,0))) | F35: =IF($A35="","",SUMIFS(工时记录!$I$5:$I$1004,工时记录!$B$5:$B$1004,$A35,工时记录!$K$5:$K$1004,"一次性")/60) | G35: =IF($A35="","",SUMIFS(工时记录!$I$5:$I$1004,工时记录!$B$5:$B$1004,$A35,工时记录!$K$5:$K$1004,"维护")/60) | H35: =IF($A35="","",SUMIFS(工时记录!$I$5:$I$1004,工时记录!$B$5:$B$1004,$A35,工时记录!$K$5:$K$1004,"专项")/60) | I35: =IF($A35="","",SUMIFS(工时记录!$I$5:$I$1004,工时记录!$B$5:$B$1004,$A35)/60) | J35: =IF(OR($A35="",E35=""),"",G35*60/E35) | K35: =IF($A35="","",COUNTIFS(互动记录!$B$5:$B$1004,$A35,互动记录!$C$5:$C$1004,"老板发送数据")) | L35: =IF(OR($A35="",E35=""),"",MIN(1,K35/E35)) | M35: =IF($A35="","",COUNTIFS(互动记录!$B$5:$B$1004,$A35,互动记录!$C$5:$C$1004,"老板主动提问/提需求")) | N35: =IF($A35="","",COUNTIFS(互动记录!$B$5:$B$1004,$A35,互动记录!$C$5:$C$1004,"周报已发送（未修改）")+COUNTIFS(互动记录!$B$5:$B$1004,$A35,互动记录!$C$5:$C$1004,"周报经修改后发送")+COUNTIFS(互动记录!$B$5:$B$1004,$A35,互动记录!$C$5:$C$1004,"周报退回重做")) | O35: =IF(OR($A35="",N35=0),"",(COUNTIFS(互动记录!$B$5:$B$1004,$A35,互动记录!$C$5:$C$1004,"周报经修改后发送")+COUNTIFS(互动记录!$B$5:$B$1004,$A35,互动记录!$C$5:$C$1004,"周报退回重做"))/N35) | P35: =IF($A35="","",COUNTIFS(互动记录!$B$5:$B$1004,$A35,互动记录!$C$5:$C$1004,"建议被采用")) | Q35: =IF($A35="","",COUNTIFS(互动记录!$B$5:$B$1004,$A35,互动记录!$C$5:$C$1004,"增值/专项线索")) | R35: =IF($A35="","",客户台账!N10) | S35: =IF($A35="","",SUMIFS(支出记录!$E$5:$E$504,支出记录!$D$5:$D$504,$A35)) | T35: =IF(OR($A35="",I35=0),"",(R35-S35)/I35)
A36: =IF(客户台账!A11="","",客户台账!A11) | B36: =IF($A36="","",客户台账!B11) | C36: =IF($A36="","",客户台账!D11) | D36: =IF($A36="","",客户台账!I11) | E36: =IF(OR($A36="",客户台账!K11="",C36<>"会员线"),"",MAX(1,ROUNDUP((MIN(客户台账!L11,$B$3)-客户台账!K11+1)/7,0))) | F36: =IF($A36="","",SUMIFS(工时记录!$I$5:$I$1004,工时记录!$B$5:$B$1004,$A36,工时记录!$K$5:$K$1004,"一次性")/60) | G36: =IF($A36="","",SUMIFS(工时记录!$I$5:$I$1004,工时记录!$B$5:$B$1004,$A36,工时记录!$K$5:$K$1004,"维护")/60) | H36: =IF($A36="","",SUMIFS(工时记录!$I$5:$I$1004,工时记录!$B$5:$B$1004,$A36,工时记录!$K$5:$K$1004,"专项")/60) | I36: =IF($A36="","",SUMIFS(工时记录!$I$5:$I$1004,工时记录!$B$5:$B$1004,$A36)/60) | J36: =IF(OR($A36="",E36=""),"",G36*60/E36) | K36: =IF($A36="","",COUNTIFS(互动记录!$B$5:$B$1004,$A36,互动记录!$C$5:$C$1004,"老板发送数据")) | L36: =IF(OR($A36="",E36=""),"",MIN(1,K36/E36)) | M36: =IF($A36="","",COUNTIFS(互动记录!$B$5:$B$1004,$A36,互动记录!$C$5:$C$1004,"老板主动提问/提需求")) | N36: =IF($A36="","",COUNTIFS(互动记录!$B$5:$B$1004,$A36,互动记录!$C$5:$C$1004,"周报已发送（未修改）")+COUNTIFS(互动记录!$B$5:$B$1004,$A36,互动记录!$C$5:$C$1004,"周报经修改后发送")+COUNTIFS(互动记录!$B$5:$B$1004,$A36,互动记录!$C$5:$C$1004,"周报退回重做")) | O36: =IF(OR($A36="",N36=0),"",(COUNTIFS(互动记录!$B$5:$B$1004,$A36,互动记录!$C$5:$C$1004,"周报经修改后发送")+COUNTIFS(互动记录!$B$5:$B$1004,$A36,互动记录!$C$5:$C$1004,"周报退回重做"))/N36) | P36: =IF($A36="","",COUNTIFS(互动记录!$B$5:$B$1004,$A36,互动记录!$C$5:$C$1004,"建议被采用")) | Q36: =IF($A36="","",COUNTIFS(互动记录!$B$5:$B$1004,$A36,互动记录!$C$5:$C$1004,"增值/专项线索")) | R36: =IF($A36="","",客户台账!N11) | S36: =IF($A36="","",SUMIFS(支出记录!$E$5:$E$504,支出记录!$D$5:$D$504,$A36)) | T36: =IF(OR($A36="",I36=0),"",(R36-S36)/I36)
A37: =IF(客户台账!A12="","",客户台账!A12) | B37: =IF($A37="","",客户台账!B12) | C37: =IF($A37="","",客户台账!D12) | D37: =IF($A37="","",客户台账!I12) | E37: =IF(OR($A37="",客户台账!K12="",C37<>"会员线"),"",MAX(1,ROUNDUP((MIN(客户台账!L12,$B$3)-客户台账!K12+1)/7,0))) | F37: =IF($A37="","",SUMIFS(工时记录!$I$5:$I$1004,工时记录!$B$5:$B$1004,$A37,工时记录!$K$5:$K$1004,"一次性")/60) | G37: =IF($A37="","",SUMIFS(工时记录!$I$5:$I$1004,工时记录!$B$5:$B$1004,$A37,工时记录!$K$5:$K$1004,"维护")/60) | H37: =IF($A37="","",SUMIFS(工时记录!$I$5:$I$1004,工时记录!$B$5:$B$1004,$A37,工时记录!$K$5:$K$1004,"专项")/60) | I37: =IF($A37="","",SUMIFS(工时记录!$I$5:$I$1004,工时记录!$B$5:$B$1004,$A37)/60) | J37: =IF(OR($A37="",E37=""),"",G37*60/E37) | K37: =IF($A37="","",COUNTIFS(互动记录!$B$5:$B$1004,$A37,互动记录!$C$5:$C$1004,"老板发送数据")) | L37: =IF(OR($A37="",E37=""),"",MIN(1,K37/E37)) | M37: =IF($A37="","",COUNTIFS(互动记录!$B$5:$B$1004,$A37,互动记录!$C$5:$C$1004,"老板主动提问/提需求")) | N37: =IF($A37="","",COUNTIFS(互动记录!$B$5:$B$1004,$A37,互动记录!$C$5:$C$1004,"周报已发送（未修改）")+COUNTIFS(互动记录!$B$5:$B$1004,$A37,互动记录!$C$5:$C$1004,"周报经修改后发送")+COUNTIFS(互动记录!$B$5:$B$1004,$A37,互动记录!$C$5:$C$1004,"周报退回重做")) | O37: =IF(OR($A37="",N37=0),"",(COUNTIFS(互动记录!$B$5:$B$1004,$A37,互动记录!$C$5:$C$1004,"周报经修改后发送")+COUNTIFS(互动记录!$B$5:$B$1004,$A37,互动记录!$C$5:$C$1004,"周报退回重做"))/N37) | P37: =IF($A37="","",COUNTIFS(互动记录!$B$5:$B$1004,$A37,互动记录!$C$5:$C$1004,"建议被采用")) | Q37: =IF($A37="","",COUNTIFS(互动记录!$B$5:$B$1004,$A37,互动记录!$C$5:$C$1004,"增值/专项线索")) | R37: =IF($A37="","",客户台账!N12) | S37: =IF($A37="","",SUMIFS(支出记录!$E$5:$E$504,支出记录!$D$5:$D$504,$A37)) | T37: =IF(OR($A37="",I37=0),"",(R37-S37)/I37)
A38: =IF(客户台账!A13="","",客户台账!A13) | B38: =IF($A38="","",客户台账!B13) | C38: =IF($A38="","",客户台账!D13) | D38: =IF($A38="","",客户台账!I13) | E38: =IF(OR($A38="",客户台账!K13="",C38<>"会员线"),"",MAX(1,ROUNDUP((MIN(客户台账!L13,$B$3)-客户台账!K13+1)/7,0))) | F38: =IF($A38="","",SUMIFS(工时记录!$I$5:$I$1004,工时记录!$B$5:$B$1004,$A38,工时记录!$K$5:$K$1004,"一次性")/60) | G38: =IF($A38="","",SUMIFS(工时记录!$I$5:$I$1004,工时记录!$B$5:$B$1004,$A38,工时记录!$K$5:$K$1004,"维护")/60) | H38: =IF($A38="","",SUMIFS(工时记录!$I$5:$I$1004,工时记录!$B$5:$B$1004,$A38,工时记录!$K$5:$K$1004,"专项")/60) | I38: =IF($A38="","",SUMIFS(工时记录!$I$5:$I$1004,工时记录!$B$5:$B$1004,$A38)/60) | J38: =IF(OR($A38="",E38=""),"",G38*60/E38) | K38: =IF($A38="","",COUNTIFS(互动记录!$B$5:$B$1004,$A38,互动记录!$C$5:$C$1004,"老板发送数据")) | L38: =IF(OR($A38="",E38=""),"",MIN(1,K38/E38)) | M38: =IF($A38="","",COUNTIFS(互动记录!$B$5:$B$1004,$A38,互动记录!$C$5:$C$1004,"老板主动提问/提需求")) | N38: =IF($A38="","",COUNTIFS(互动记录!$B$5:$B$1004,$A38,互动记录!$C$5:$C$1004,"周报已发送（未修改）")+COUNTIFS(互动记录!$B$5:$B$1004,$A38,互动记录!$C$5:$C$1004,"周报经修改后发送")+COUNTIFS(互动记录!$B$5:$B$1004,$A38,互动记录!$C$5:$C$1004,"周报退回重做")) | O38: =IF(OR($A38="",N38=0),"",(COUNTIFS(互动记录!$B$5:$B$1004,$A38,互动记录!$C$5:$C$1004,"周报经修改后发送")+COUNTIFS(互动记录!$B$5:$B$1004,$A38,互动记录!$C$5:$C$1004,"周报退回重做"))/N38) | P38: =IF($A38="","",COUNTIFS(互动记录!$B$5:$B$1004,$A38,互动记录!$C$5:$C$1004,"建议被采用")) | Q38: =IF($A38="","",COUNTIFS(互动记录!$B$5:$B$1004,$A38,互动记录!$C$5:$C$1004,"增值/专项线索")) | R38: =IF($A38="","",客户台账!N13) | S38: =IF($A38="","",SUMIFS(支出记录!$E$5:$E$504,支出记录!$D$5:$D$504,$A38)) | T38: =IF(OR($A38="",I38=0),"",(R38-S38)/I38)
A39: =IF(客户台账!A14="","",客户台账!A14) | B39: =IF($A39="","",客户台账!B14) | C39: =IF($A39="","",客户台账!D14) | D39: =IF($A39="","",客户台账!I14) | E39: =IF(OR($A39="",客户台账!K14="",C39<>"会员线"),"",MAX(1,ROUNDUP((MIN(客户台账!L14,$B$3)-客户台账!K14+1)/7,0))) | F39: =IF($A39="","",SUMIFS(工时记录!$I$5:$I$1004,工时记录!$B$5:$B$1004,$A39,工时记录!$K$5:$K$1004,"一次性")/60) | G39: =IF($A39="","",SUMIFS(工时记录!$I$5:$I$1004,工时记录!$B$5:$B$1004,$A39,工时记录!$K$5:$K$1004,"维护")/60) | H39: =IF($A39="","",SUMIFS(工时记录!$I$5:$I$1004,工时记录!$B$5:$B$1004,$A39,工时记录!$K$5:$K$1004,"专项")/60) | I39: =IF($A39="","",SUMIFS(工时记录!$I$5:$I$1004,工时记录!$B$5:$B$1004,$A39)/60) | J39: =IF(OR($A39="",E39=""),"",G39*60/E39) | K39: =IF($A39="","",COUNTIFS(互动记录!$B$5:$B$1004,$A39,互动记录!$C$5:$C$1004,"老板发送数据")) | L39: =IF(OR($A39="",E39=""),"",MIN(1,K39/E39)) | M39: =IF($A39="","",COUNTIFS(互动记录!$B$5:$B$1004,$A39,互动记录!$C$5:$C$1004,"老板主动提问/提需求")) | N39: =IF($A39="","",COUNTIFS(互动记录!$B$5:$B$1004,$A39,互动记录!$C$5:$C$1004,"周报已发送（未修改）")+COUNTIFS(互动记录!$B$5:$B$1004,$A39,互动记录!$C$5:$C$1004,"周报经修改后发送")+COUNTIFS(互动记录!$B$5:$B$1004,$A39,互动记录!$C$5:$C$1004,"周报退回重做")) | O39: =IF(OR($A39="",N39=0),"",(COUNTIFS(互动记录!$B$5:$B$1004,$A39,互动记录!$C$5:$C$1004,"周报经修改后发送")+COUNTIFS(互动记录!$B$5:$B$1004,$A39,互动记录!$C$5:$C$1004,"周报退回重做"))/N39) | P39: =IF($A39="","",COUNTIFS(互动记录!$B$5:$B$1004,$A39,互动记录!$C$5:$C$1004,"建议被采用")) | Q39: =IF($A39="","",COUNTIFS(互动记录!$B$5:$B$1004,$A39,互动记录!$C$5:$C$1004,"增值/专项线索")) | R39: =IF($A39="","",客户台账!N14) | S39: =IF($A39="","",SUMIFS(支出记录!$E$5:$E$504,支出记录!$D$5:$D$504,$A39)) | T39: =IF(OR($A39="",I39=0),"",(R39-S39)/I39)
A40: =IF(客户台账!A15="","",客户台账!A15) | B40: =IF($A40="","",客户台账!B15) | C40: =IF($A40="","",客户台账!D15) | D40: =IF($A40="","",客户台账!I15) | E40: =IF(OR($A40="",客户台账!K15="",C40<>"会员线"),"",MAX(1,ROUNDUP((MIN(客户台账!L15,$B$3)-客户台账!K15+1)/7,0))) | F40: =IF($A40="","",SUMIFS(工时记录!$I$5:$I$1004,工时记录!$B$5:$B$1004,$A40,工时记录!$K$5:$K$1004,"一次性")/60) | G40: =IF($A40="","",SUMIFS(工时记录!$I$5:$I$1004,工时记录!$B$5:$B$1004,$A40,工时记录!$K$5:$K$1004,"维护")/60) | H40: =IF($A40="","",SUMIFS(工时记录!$I$5:$I$1004,工时记录!$B$5:$B$1004,$A40,工时记录!$K$5:$K$1004,"专项")/60) | I40: =IF($A40="","",SUMIFS(工时记录!$I$5:$I$1004,工时记录!$B$5:$B$1004,$A40)/60) | J40: =IF(OR($A40="",E40=""),"",G40*60/E40) | K40: =IF($A40="","",COUNTIFS(互动记录!$B$5:$B$1004,$A40,互动记录!$C$5:$C$1004,"老板发送数据")) | L40: =IF(OR($A40="",E40=""),"",MIN(1,K40/E40)) | M40: =IF($A40="","",COUNTIFS(互动记录!$B$5:$B$1004,$A40,互动记录!$C$5:$C$1004,"老板主动提问/提需求")) | N40: =IF($A40="","",COUNTIFS(互动记录!$B$5:$B$1004,$A40,互动记录!$C$5:$C$1004,"周报已发送（未修改）")+COUNTIFS(互动记录!$B$5:$B$1004,$A40,互动记录!$C$5:$C$1004,"周报经修改后发送")+COUNTIFS(互动记录!$B$5:$B$1004,$A40,互动记录!$C$5:$C$1004,"周报退回重做")) | O40: =IF(OR($A40="",N40=0),"",(COUNTIFS(互动记录!$B$5:$B$1004,$A40,互动记录!$C$5:$C$1004,"周报经修改后发送")+COUNTIFS(互动记录!$B$5:$B$1004,$A40,互动记录!$C$5:$C$1004,"周报退回重做"))/N40) | P40: =IF($A40="","",COUNTIFS(互动记录!$B$5:$B$1004,$A40,互动记录!$C$5:$C$1004,"建议被采用")) | Q40: =IF($A40="","",COUNTIFS(互动记录!$B$5:$B$1004,$A40,互动记录!$C$5:$C$1004,"增值/专项线索")) | R40: =IF($A40="","",客户台账!N15) | S40: =IF($A40="","",SUMIFS(支出记录!$E$5:$E$504,支出记录!$D$5:$D$504,$A40)) | T40: =IF(OR($A40="",I40=0),"",(R40-S40)/I40)
A41: =IF(客户台账!A16="","",客户台账!A16) | B41: =IF($A41="","",客户台账!B16) | C41: =IF($A41="","",客户台账!D16) | D41: =IF($A41="","",客户台账!I16) | E41: =IF(OR($A41="",客户台账!K16="",C41<>"会员线"),"",MAX(1,ROUNDUP((MIN(客户台账!L16,$B$3)-客户台账!K16+1)/7,0))) | F41: =IF($A41="","",SUMIFS(工时记录!$I$5:$I$1004,工时记录!$B$5:$B$1004,$A41,工时记录!$K$5:$K$1004,"一次性")/60) | G41: =IF($A41="","",SUMIFS(工时记录!$I$5:$I$1004,工时记录!$B$5:$B$1004,$A41,工时记录!$K$5:$K$1004,"维护")/60) | H41: =IF($A41="","",SUMIFS(工时记录!$I$5:$I$1004,工时记录!$B$5:$B$1004,$A41,工时记录!$K$5:$K$1004,"专项")/60) | I41: =IF($A41="","",SUMIFS(工时记录!$I$5:$I$1004,工时记录!$B$5:$B$1004,$A41)/60) | J41: =IF(OR($A41="",E41=""),"",G41*60/E41) | K41: =IF($A41="","",COUNTIFS(互动记录!$B$5:$B$1004,$A41,互动记录!$C$5:$C$1004,"老板发送数据")) | L41: =IF(OR($A41="",E41=""),"",MIN(1,K41/E41)) | M41: =IF($A41="","",COUNTIFS(互动记录!$B$5:$B$1004,$A41,互动记录!$C$5:$C$1004,"老板主动提问/提需求")) | N41: =IF($A41="","",COUNTIFS(互动记录!$B$5:$B$1004,$A41,互动记录!$C$5:$C$1004,"周报已发送（未修改）")+COUNTIFS(互动记录!$B$5:$B$1004,$A41,互动记录!$C$5:$C$1004,"周报经修改后发送")+COUNTIFS(互动记录!$B$5:$B$1004,$A41,互动记录!$C$5:$C$1004,"周报退回重做")) | O41: =IF(OR($A41="",N41=0),"",(COUNTIFS(互动记录!$B$5:$B$1004,$A41,互动记录!$C$5:$C$1004,"周报经修改后发送")+COUNTIFS(互动记录!$B$5:$B$1004,$A41,互动记录!$C$5:$C$1004,"周报退回重做"))/N41) | P41: =IF($A41="","",COUNTIFS(互动记录!$B$5:$B$1004,$A41,互动记录!$C$5:$C$1004,"建议被采用")) | Q41: =IF($A41="","",COUNTIFS(互动记录!$B$5:$B$1004,$A41,互动记录!$C$5:$C$1004,"增值/专项线索")) | R41: =IF($A41="","",客户台账!N16) | S41: =IF($A41="","",SUMIFS(支出记录!$E$5:$E$504,支出记录!$D$5:$D$504,$A41)) | T41: =IF(OR($A41="",I41=0),"",(R41-S41)/I41)
... A79: =IF(客户台账!A54="","",客户台账!A54) | B79: =IF($A79="","",客户台账!B54) | C79: =IF($A79="","",客户台账!D54) | D79: =IF($A79="","",客户台账!I54) | E79: =IF(OR($A79="",客户台账!K54="",C79<>"会员线"),"",MAX(1,ROUNDUP((MIN(客户台账!L54,$B$3)-客户台账!K54+1)/7,0))) | F79: =IF($A79="","",SUMIFS(工时记录!$I$5:$I$1004,工时记录!$B$5:$B$1004,$A79,工时记录!$K$5:$K$1004,"一次性")/60) | G79: =IF($A79="","",SUMIFS(工时记录!$I$5:$I$1004,工时记录!$B$5:$B$1004,$A79,工时记录!$K$5:$K$1004,"维护")/60) | H79: =IF($A79="","",SUMIFS(工时记录!$I$5:$I$1004,工时记录!$B$5:$B$1004,$A79,工时记录!$K$5:$K$1004,"专项")/60) | I79: =IF($A79="","",SUMIFS(工时记录!$I$5:$I$1004,工时记录!$B$5:$B$1004,$A79)/60) | J79: =IF(OR($A79="",E79=""),"",G79*60/E79) | K79: =IF($A79="","",COUNTIFS(互动记录!$B$5:$B$1004,$A79,互动记录!$C$5:$C$1004,"老板发送数据")) | L79: =IF(OR($A79="",E79=""),"",MIN(1,K79/E79)) | M79: =IF($A79="","",COUNTIFS(互动记录!$B$5:$B$1004,$A79,互动记录!$C$5:$C$1004,"老板主动提问/提需求")) | N79: =IF($A79="","",COUNTIFS(互动记录!$B$5:$B$1004,$A79,互动记录!$C$5:$C$1004,"周报已发送（未修改）")+COUNTIFS(互动记录!$B$5:$B$1004,$A79,互动记录!$C$5:$C$1004,"周报经修改后发送")+COUNTIFS(互动记录!$B$5:$B$1004,$A79,互动记录!$C$5:$C$1004,"周报退回重做")) | O79: =IF(OR($A79="",N79=0),"",(COUNTIFS(互动记录!$B$5:$B$1004,$A79,互动记录!$C$5:$C$1004,"周报经修改后发送")+COUNTIFS(互动记录!$B$5:$B$1004,$A79,互动记录!$C$5:$C$1004,"周报退回重做"))/N79) | P79: =IF($A79="","",COUNTIFS(互动记录!$B$5:$B$1004,$A79,互动记录!$C$5:$C$1004,"建议被采用")) | Q79: =IF($A79="","",COUNTIFS(互动记录!$B$5:$B$1004,$A79,互动记录!$C$5:$C$1004,"增值/专项线索")) | R79: =IF($A79="","",客户台账!N54) | S79: =IF($A79="","",SUMIFS(支出记录!$E$5:$E$504,支出记录!$D$5:$D$504,$A79)) | T79: =IF(OR($A79="",I79=0),"",(R79-S79)/I79)

Sheet 客户筛选
A1: 客户筛选评分表
A2: 依据 D02 第十三节（五项优先条件 + 慎重项）与 B08 附录A。每项 0=没有/不清楚，1=部分具备，2=明确具备。
A4: 企业编号 | B4: 企业简称 | C4: 行业 | D4: 来源渠道 | E4: 拟进入线别 | F4: 有真实问题 0–2 | G4: 有合作意愿 0–2 | H4: 有持续需求 0–2 | I4: 可合理交付 0–2 | J4: 有付费可能 0–2 | K4: 慎重项 | L4: 得分 (满分10) | M4: 系统建议 | N4: 顾问最终决定 | O4: 老板原话：最迫切的问题 | P4: （专项）未来90天要做的关键决定 | Q4: 备注
A5: 示例-01 | B5: 黔味商贸 | C5: 商贸批发 | D5: 熟人介绍 | E5: 会员线 | F5: 2 | G5: 2 | H5: 2 | I5: 1 | J5: 1 | K5: 无 | L5: =IF(A5="","",SUM(F5:J5)) | M5: =IF(A5="","",IF(AND(K5<>"",K5<>"无"),"慎重：顾问判断",IF(L5>=参数!$F$14,"强烈建议",IF(L5>=参数!$F$15,"可以试点","暂不接")))) | N5: 接 | O5: 销售还行，但钱总是不够用，应收越来越多 | Q5: 示例行，使用前删除
L6: =IF(A6="","",SUM(F6:J6)) | M6: =IF(A6="","",IF(AND(K6<>"",K6<>"无"),"慎重：顾问判断",IF(L6>=参数!$F$14,"强烈建议",IF(L6>=参数!$F$15,"可以试点","暂不接"))))
L7: =IF(A7="","",SUM(F7:J7)) | M7: =IF(A7="","",IF(AND(K7<>"",K7<>"无"),"慎重：顾问判断",IF(L7>=参数!$F$14,"强烈建议",IF(L7>=参数!$F$15,"可以试点","暂不接"))))
L8: =IF(A8="","",SUM(F8:J8)) | M8: =IF(A8="","",IF(AND(K8<>"",K8<>"无"),"慎重：顾问判断",IF(L8>=参数!$F$14,"强烈建议",IF(L8>=参数!$F$15,"可以试点","暂不接"))))
L9: =IF(A9="","",SUM(F9:J9)) | M9: =IF(A9="","",IF(AND(K9<>"",K9<>"无"),"慎重：顾问判断",IF(L9>=参数!$F$14,"强烈建议",IF(L9>=参数!$F$15,"可以试点","暂不接"))))
L10: =IF(A10="","",SUM(F10:J10)) | M10: =IF(A10="","",IF(AND(K10<>"",K10<>"无"),"慎重：顾问判断",IF(L10>=参数!$F$14,"强烈建议",IF(L10>=参数!$F$15,"可以试点","暂不接"))))
L11: =IF(A11="","",SUM(F11:J11)) | M11: =IF(A11="","",IF(AND(K11<>"",K11<>"无"),"慎重：顾问判断",IF(L11>=参数!$F$14,"强烈建议",IF(L11>=参数!$F$15,"可以试点","暂不接"))))
L12: =IF(A12="","",SUM(F12:J12)) | M12: =IF(A12="","",IF(AND(K12<>"",K12<>"无"),"慎重：顾问判断",IF(L12>=参数!$F$14,"强烈建议",IF(L12>=参数!$F$15,"可以试点","暂不接"))))
L13: =IF(A13="","",SUM(F13:J13)) | M13: =IF(A13="","",IF(AND(K13<>"",K13<>"无"),"慎重：顾问判断",IF(L13>=参数!$F$14,"强烈建议",IF(L13>=参数!$F$15,"可以试点","暂不接"))))
L14: =IF(A14="","",SUM(F14:J14)) | M14: =IF(A14="","",IF(AND(K14<>"",K14<>"无"),"慎重：顾问判断",IF(L14>=参数!$F$14,"强烈建议",IF(L14>=参数!$F$15,"可以试点","暂不接"))))
L15: =IF(A15="","",SUM(F15:J15)) | M15: =IF(A15="","",IF(AND(K15<>"",K15<>"无"),"慎重：顾问判断",IF(L15>=参数!$F$14,"强烈建议",IF(L15>=参数!$F$15,"可以试点","暂不接"))))
L16: =IF(A16="","",SUM(F16:J16)) | M16: =IF(A16="","",IF(AND(K16<>"",K16<>"无"),"慎重：顾问判断",IF(L16>=参数!$F$14,"强烈建议",IF(L16>=参数!$F$15,"可以试点","暂不接"))))
L17: =IF(A17="","",SUM(F17:J17)) | M17: =IF(A17="","",IF(AND(K17<>"",K17<>"无"),"慎重：顾问判断",IF(L17>=参数!$F$14,"强烈建议",IF(L17>=参数!$F$15,"可以试点","暂不接"))))
... L104: =IF(A104="","",SUM(F104:J104)) | M104: =IF(A104="","",IF(AND(K104<>"",K104<>"无"),"慎重：顾问判断",IF(L104>=参数!$F$14,"强烈建议",IF(L104>=参数!$F$15,"可以试点","暂不接"))))

Sheet 客户台账
A1: 客户台账（会员线 + 专项线）
A2: 每家企业一行，企业编号全表唯一。KPI看板按本表前50行逐行汇总。
A4: 企业编号 | B4: 企业简称 | C4: 行业 | D4: 线别 | E4: 来源渠道 | F4: 联系人及角色 | G4: 初次接触日期 | H4: 主要需求/老板主诉 | I4: 当前状态 | J4: 产品/套餐 | K4: 体验/项目开始日 | L4: 30天体验结束日 (会员线自动) | M4: 专项验收日 | N4: 累计实收(元) | O4: 转正/成交日期 | P4: 未转正/未成交原因 | Q4: 下次跟进日期 | R4: 备注
A5: 示例-01 | B5: 黔味商贸 | C5: 商贸批发 | D5: 会员线 | E5: 熟人介绍 | F5: 王总/老板 | G5: 46305 | H5: 应收增长快于销售，现金紧 | I5: 体验中（已付99元） | J5: 99元体验 | K5: 46310 | L5: =IF(OR(K5="",D5<>"会员线"),"",K5+29) | N5: 99 | Q5: 46317 | R5: 示例行，使用前删除
A6: 示例-02 | B6: 某连锁餐饮 | C6: 餐饮 | D6: 专项线 | E6: 客户转介绍 | F6: 李总/创始人 | G6: 46307 | H6: 第4家店该不该开 | I6: 已签约（专项） | J6: P03扩张决策 | K6: 46315 | L6: =IF(OR(K6="",D6<>"会员线"),"",K6+29) | N6: 6400 | O6: 46313 | Q6: 46322 | R6: 示例行，首付款50%
L7: =IF(OR(K7="",D7<>"会员线"),"",K7+29)
L8: =IF(OR(K8="",D8<>"会员线"),"",K8+29)
L9: =IF(OR(K9="",D9<>"会员线"),"",K9+29)
L10: =IF(OR(K10="",D10<>"会员线"),"",K10+29)
L11: =IF(OR(K11="",D11<>"会员线"),"",K11+29)
L12: =IF(OR(K12="",D12<>"会员线"),"",K12+29)
L13: =IF(OR(K13="",D13<>"会员线"),"",K13+29)
L14: =IF(OR(K14="",D14<>"会员线"),"",K14+29)
L15: =IF(OR(K15="",D15<>"会员线"),"",K15+29)
L16: =IF(OR(K16="",D16<>"会员线"),"",K16+29)
L17: =IF(OR(K17="",D17<>"会员线"),"",K17+29)
L18: =IF(OR(K18="",D18<>"会员线"),"",K18+29)
... L54: =IF(OR(K54="",D54<>"会员线"),"",K54+29)

Sheet 工时记录
A1: 顾问工时记录
A2: 每做完一件事记一行。可填开始/结束时间，或直接填“手填人工分钟”（优先）。共享任务企业编号填“共享”，非客户工作填“内部”。
A4: 日期 | B4: 企业编号 | C4: 线别 | D4: 工作类型 | E4: 内容简述 | F4: 开始时间 | G4: 结束时间 | H4: 手填人工分钟 | I4: 计入人工分钟 | J4: AI运行分钟 | K4: 工时性质 | L4: 时间预算类别 | M4: 试运营超配？ | N4: 产生增值线索？ | O4: 备注
A5: 46310 | B5: 示例-01 | C5: 会员线 | D5: 首次访谈 | E5: 老板主诉与经营模型梳理 | F5: 0.58333333 | G5: 0.64583333 | I5: =IF(H5<>"",H5,IF(AND(F5<>"",G5<>""),ROUND((G5-F5)*1440,0),"")) | J5: 0 | K5: =IF(D5="","",IFERROR(VLOOKUP(D5,参数!$A$5:$C$24,2,0),"")) | L5: =IF(D5="","",IFERROR(VLOOKUP(D5,参数!$A$5:$C$24,3,0),"")) | M5: 否 | N5: 否 | O5: 示例行
A6: 46311 | B6: 示例-01 | C6: 会员线 | D6: 首次体检分析与审核 | E6: 应收账龄与客户集中度 | H6: 120 | I6: =IF(H6<>"",H6,IF(AND(F6<>"",G6<>""),ROUND((G6-F6)*1440,0),"")) | J6: 25 | K6: =IF(D6="","",IFERROR(VLOOKUP(D6,参数!$A$5:$C$24,2,0),"")) | L6: =IF(D6="","",IFERROR(VLOOKUP(D6,参数!$A$5:$C$24,3,0),"")) | M6: 否 | N6: 是 | O6: 示例行
A7: 46315 | B7: 示例-02 | C7: 专项线 | D7: 专项交付 | E7: 单店模型与投资测算 | H7: 240 | I7: =IF(H7<>"",H7,IF(AND(F7<>"",G7<>""),ROUND((G7-F7)*1440,0),"")) | J7: 30 | K7: =IF(D7="","",IFERROR(VLOOKUP(D7,参数!$A$5:$C$24,2,0),"")) | L7: =IF(D7="","",IFERROR(VLOOKUP(D7,参数!$A$5:$C$24,3,0),"")) | M7: 否 | N7: 否 | O7: 示例行
A8: 46315 | B8: 共享 | C8: 共享/内部 | D8: 共享信息整理与批量任务 | E8: 本周政策与补贴整理 | H8: 60 | I8: =IF(H8<>"",H8,IF(AND(F8<>"",G8<>""),ROUND((G8-F8)*1440,0),"")) | J8: 20 | K8: =IF(D8="","",IFERROR(VLOOKUP(D8,参数!$A$5:$C$24,2,0),"")) | L8: =IF(D8="","",IFERROR(VLOOKUP(D8,参数!$A$5:$C$24,3,0),"")) | M8: 否 | N8: 否 | O8: 示例行
I9: =IF(H9<>"",H9,IF(AND(F9<>"",G9<>""),ROUND((G9-F9)*1440,0),"")) | K9: =IF(D9="","",IFERROR(VLOOKUP(D9,参数!$A$5:$C$24,2,0),"")) | L9: =IF(D9="","",IFERROR(VLOOKUP(D9,参数!$A$5:$C$24,3,0),""))
I10: =IF(H10<>"",H10,IF(AND(F10<>"",G10<>""),ROUND((G10-F10)*1440,0),"")) | K10: =IF(D10="","",IFERROR(VLOOKUP(D10,参数!$A$5:$C$24,2,0),"")) | L10: =IF(D10="","",IFERROR(VLOOKUP(D10,参数!$A$5:$C$24,3,0),""))
I11: =IF(H11<>"",H11,IF(AND(F11<>"",G11<>""),ROUND((G11-F11)*1440,0),"")) | K11: =IF(D11="","",IFERROR(VLOOKUP(D11,参数!$A$5:$C$24,2,0),"")) | L11: =IF(D11="","",IFERROR(VLOOKUP(D11,参数!$A$5:$C$24,3,0),""))
I12: =IF(H12<>"",H12,IF(AND(F12<>"",G12<>""),ROUND((G12-F12)*1440,0),"")) | K12: =IF(D12="","",IFERROR(VLOOKUP(D12,参数!$A$5:$C$24,2,0),"")) | L12: =IF(D12="","",IFERROR(VLOOKUP(D12,参数!$A$5:$C$24,3,0),""))
I13: =IF(H13<>"",H13,IF(AND(F13<>"",G13<>""),ROUND((G13-F13)*1440,0),"")) | K13: =IF(D13="","",IFERROR(VLOOKUP(D13,参数!$A$5:$C$24,2,0),"")) | L13: =IF(D13="","",IFERROR(VLOOKUP(D13,参数!$A$5:$C$24,3,0),""))
I14: =IF(H14<>"",H14,IF(AND(F14<>"",G14<>""),ROUND((G14-F14)*1440,0),"")) | K14: =IF(D14="","",IFERROR(VLOOKUP(D14,参数!$A$5:$C$24,2,0),"")) | L14: =IF(D14="","",IFERROR(VLOOKUP(D14,参数!$A$5:$C$24,3,0),""))
I15: =IF(H15<>"",H15,IF(AND(F15<>"",G15<>""),ROUND((G15-F15)*1440,0),"")) | K15: =IF(D15="","",IFERROR(VLOOKUP(D15,参数!$A$5:$C$24,2,0),"")) | L15: =IF(D15="","",IFERROR(VLOOKUP(D15,参数!$A$5:$C$24,3,0),""))
I16: =IF(H16<>"",H16,IF(AND(F16<>"",G16<>""),ROUND((G16-F16)*1440,0),"")) | K16: =IF(D16="","",IFERROR(VLOOKUP(D16,参数!$A$5:$C$24,2,0),"")) | L16: =IF(D16="","",IFERROR(VLOOKUP(D16,参数!$A$5:$C$24,3,0),""))
I17: =IF(H17<>"",H17,IF(AND(F17<>"",G17<>""),ROUND((G17-F17)*1440,0),"")) | K17: =IF(D17="","",IFERROR(VLOOKUP(D17,参数!$A$5:$C$24,2,0),"")) | L17: =IF(D17="","",IFERROR(VLOOKUP(D17,参数!$A$5:$C$24,3,0),""))
I18: =IF(H18<>"",H18,IF(AND(F18<>"",G18<>""),ROUND((G18-F18)*1440,0),"")) | K18: =IF(D18="","",IFERROR(VLOOKUP(D18,参数!$A$5:$C$24,2,0),"")) | L18: =IF(D18="","",IFERROR(VLOOKUP(D18,参数!$A$5:$C$24,3,0),""))
I19: =IF(H19<>"",H19,IF(AND(F19<>"",G19<>""),ROUND((G19-F19)*1440,0),"")) | K19: =IF(D19="","",IFERROR(VLOOKUP(D19,参数!$A$5:$C$24,2,0),"")) | L19: =IF(D19="","",IFERROR(VLOOKUP(D19,参数!$A$5:$C$24,3,0),""))
I20: =IF(H20<>"",H20,IF(AND(F20<>"",G20<>""),ROUND((G20-F20)*1440,0),"")) | K20: =IF(D20="","",IFERROR(VLOOKUP(D20,参数!$A$5:$C$24,2,0),"")) | L20: =IF(D20="","",IFERROR(VLOOKUP(D20,参数!$A$5:$C$24,3,0),""))
... I1004: =IF(H1004<>"",H1004,IF(AND(F1004<>"",G1004<>""),ROUND((G1004-F1004)*1440,0),"")) | K1004: =IF(D1004="","",IFERROR(VLOOKUP(D1004,参数!$A$5:$C$24,2,0),"")) | L1004: =IF(D1004="","",IFERROR(VLOOKUP(D1004,参数!$A$5:$C$24,3,0),""))

Sheet 互动记录
A1: 客户互动与质量事件记录
A2: 老板的主动行为、周报发送结果和质量事件逐条记录，用于计算数据发送率、修改率、主动性等 KPI。
A4: 日期 | B4: 企业编号 | C4: 事件类型 | D4: 说明 | E4: 关联消息/文件
A5: 46312 | B5: 示例-01 | C5: 老板发送数据 | D5: 9月销售与应收明细 Excel | E5: 黔味商贸_销售_20261017.xlsx
A6: 46315 | B6: 示例-01 | C6: 周报经修改后发送 | D6: 建议空泛，补充了具体客户名单
A7: 46316 | B7: 示例-01 | C7: 老板主动提问/提需求 | D7: 问某大客户是否该收紧账期

Sheet 支出记录
A1: 现金支出记录
A2: 按实际账单记录。已包含在固定订阅内的用量不再按客户重复计入（F01 10.4）。增量支出请填关联企业编号。
A4: 日期 | B4: 类别 | C4: 固定/增量 | D4: 关联企业编号 | E4: 金额(元) | F4: 说明/凭证
A5: 46296 | B5: AI与模型订阅 | C5: 固定 | E5: 200 | F5: 示例：大模型API月度预充值
A6: 46310 | B6: 交通 | C6: 增量 | D6: 示例-01 | E6: 30 | F6: 示例：上门访谈往返

Sheet 30天复盘
A1: 30天企业复盘表
A2: 体验结束时与老板逐项沟通（D01 第十一章、总目录 D06）。A–D 四项为顾问内部判断。
A4: 企业编号 | B4: 复盘日期 | C4: 最有价值的服务 | D4: 完全没价值的 | E4: 没有看的 | F4: 想继续的 | G4: 愿意付费的服务 | H4: 愿意付多少(元/月) | I4: 是否推荐朋友 | J4: 是否产生增值/专项需求 | K4: 是否转正 | L4: 选择套餐 | M4: 未转正原因 | N4: A 需求成立？ | O4: B 服务成立？ | P4: C 交付成立？ | Q4: D 商业成立？ | R4: 下一步
A5: 示例-01 | B5: 46339 | C5: 应收账龄提醒 | D5: 政策资讯 | E5: 月度总结 | F5: 每周应收与大客户提醒 | G5: 周报+问诊 | H5: 399 | I5: 是 | J5: 是 | K5: 是 | L5: 标准版399 | N5: 成立 | O5: 成立 | P5: 存疑 | Q5: 存疑 | R5: 示例行：关注第2个月实际人工

Sheet 参数
A1: 参数与下拉列表
A2: 黄色单元格可按实际情况修改；修改后各表下拉与汇总自动更新。
A4: 工作类型 | B4: 工时性质 | C4: 时间预算类别 | E4: 时间预算类别 | F4: 月度预留小时 | H4: 线别 | I4: 客户状态 | J4: 产品/套餐 | K4: 互动事件 | L4: 支出类别 | M4: 是/否 | N4: 慎重项 | O4: 复盘判断 | Q4: 支出性质
A5: 获客沟通 | B5: 一次性 | C5: 客户开发与销售 | E5: 客户服务 | F5: 65 | H5: 会员线 | I5: 线索 | J5: 99元体验 | K5: 老板主动提问/提需求 | L5: AI与模型订阅 | M5: 是 | N5: 无 | O5: 成立 | Q5: 固定
A6: 专项售前（初筛/报价） | B6: 一次性 | C6: 客户开发与销售 | E6: 客户开发与销售 | F6: 20 | H6: 专项线 | I6: 有效沟通 | J6: 基础版199 | K6: 老板发送数据 | L6: 工具软件 | M6: 否 | N6: 需求过重 | O6: 存疑 | Q6: 增量
A7: 首次访谈 | B7: 一次性 | C7: 客户服务 | E7: 产品及AI工作流 | F7: 20 | H7: 共享/内部 | I7: 深入介绍/初筛 | J7: 标准版399 | K7: 周报已发送（未修改） | L7: 存储备份 | N7: 配合不足 | O7: 不成立
A8: 建档与资料整理 | B8: 一次性 | C8: 客户服务 | E8: 一般运营管理 | F8: 15 | I8: 体验中（已付99元） | J8: 顾问版1299+ | K8: 周报经修改后发送 | L8: 通信 | N8: 高度依赖资质
A9: 首次体检分析与审核 | B9: 一次性 | C9: 客户服务 | E9: 协会公益共建 | F9: 12 | I9: 体验结束待转正 | J9: 会员专项简析 | K9: 周报退回重做 | L9: 交通 | N9: 无法保证服务质量
A10: 报告解读 | B10: 一次性 | C10: 客户服务 | E10: 合计 | F10: =SUM(F5:F9) | I10: 正式会员 | J10: P01专项诊断 | K10: 老板阅读反馈 | L10: 推广与销售材料
A11: 周报/简报审核 | B11: 维护 | C11: 客户服务 | E11: 来源：C02 V1.1 第十二章（6小时/天×22天=132小时/月）。 | I11: 已报价（专项） | J11: P02改善行动 | K11: 建议被采用 | L11: 记账财税
A12: 风险与机会提醒 | B12: 维护 | C12: 客户服务 | I12: 已签约（专项） | J12: P03扩张决策 | K12: 增值/专项线索 | L12: 专业外包
A13: 经营问诊 | B13: 维护 | C13: 客户服务 | E13: 客户筛选阈值（满分10） | I13: 交付中（专项） | J13: P04 AI数字化 | K13: 转介绍 | L13: 设备
A14: 材料支持 | B14: 维护 | C14: 客户服务 | E14: 强烈建议 ≥ | F14: 8 | I14: 已验收（专项） | J14: P05顾问陪跑 | K14: 发错对象 | L14: 其他
A15: 数据更新与处理 | B15: 维护 | C15: 客户服务 | E15: 可以试点 ≥ | F15: 6 | I15: 未转正/未成交 | K15: 数字错误
A16: 资源对接 | B16: 维护 | C16: 客户服务 | E16: 内部建议值，非验证结论；按首批实际情况调整。 | I16: 流失
A17: 会议与面谈（含交通） | B17: 维护 | C17: 客户服务
A18: 月末复盘与续费沟通 | B18: 维护 | C18: 客户服务
A19: 返工与修改 | B19: 维护 | C19: 客户服务
A20: 专项交付 | B20: 专项 | C20: 客户服务
A21: 共享信息整理与批量任务 | B21: 共享 | C21: 客户服务
A22: 产品与AI工作流开发 | B22: 非服务 | C22: 产品及AI工作流
A23: 一般运营管理 | B23: 非服务 | C23: 一般运营管理
A24: 协会公益共建 | B24: 非服务 | C24: 协会公益共建
A26: 工时性质：一次性=建档与首次服务；维护=稳定期周期服务；专项=高级专项交付；共享=多客户共用的批量工作；非服务=不计入客户服务预算。依据 F01 第十章、D01 7.1。
A29: KPI 目标值
A30: 指标 | B30: 目标 | C30: 来源
A31: 体验企业数（家） | B31: 5 | C31: D01/F01：5–10家
A32: 正式转正企业数（家） | B32: 3 | C32: F01：至少3家；MVP：≥2家
A33: 数据按时发送率 | B33: 0.6 | C33: MVP：≥60%
A34: 周报修改率（上限） | B34: 0.3 | C34: MVP：第4周≤30%
A35: 每企业每周维护人工（分钟，上限） | B35: 15 | C35: MVP：≤15分钟
A36: 发错对象（次，上限） | B36: 0 | C36: MVP：0
A37: 主动提问企业数（家） | B37: 3 | C37: MVP：≥3家
A38: 专项正式报价数 | B38: 3 | C38: B08：至少3份
A39: 专项成交数 | B39: 1 | C39: B08：争取1–2单
