Workbook

Sheet 说明
A1: H02｜单客户经济模型与90天预算 V1.0
A2: 版本日期：2026-10-12 · 依据：C02 V1.1、F01、F02、MVP 第九章、B01、B08、BP V0.4
A4: 用途 | B4: 把散落在 C02/F01/F02/BP/MVP/B08 中的价格、成本、工时口径集中成一个可调参数的模型：会员单客经济、规模情景、专项单项目经济、90天双线情景和90天预算。
A5: 颜色 | B5: 蓝字浅黄底 = 可改输入；黑字 = 公式；绿字 = 引用其他工作表。所有参数集中在“假设”和“90天预算”两张表。
A6: 口径 | B6: 现金口径（C02 V1.1）：创始人暂不领工资，工时不计现金成本，单独作为产能约束（客户服务预算65小时/月）。所有“结余”都不是净利润：未计税费、客户流失与退款、获客费用、创始人薪酬。
A7: D03-A 重建 | B7: 原《D03-A V1.2》缺失。1298元/月总额有文档出处；分项金额是本次按 C02 2.1 的支出类别和 MVP 第九章区间重建的估计，请按实际账单修正。若改后合计不等于1298，“90天预算”会提示需同步修订 C02/F02/BP。
A8: 自校验 | B8: “会员单客经济”第10行应为 7/4/2；“规模情景”MRR 应为 8980/13470/22450，结余应为 7462/11242/19102，各情景工时应与 C02 第十二章一致。数字对不上说明假设已被修改。
A9: 占位假设 | B9: P02–P04 工时与外包占比、会员专项简析工时、法务审核费用、体验转化率、付费月数均无文档出处，为占位值，首批真实数据出来后用 D05 工具包的记录替换。
A10: 配套 | B10: D05 试点运营工具包记录真实数据；本模型做事前测算。90天后用真实值回填“假设”，对照 BP V0.4 17.7 做主线裁决。

Sheet 假设
A1: 关键假设（所有可调参数都在本表）
A2: 蓝字浅黄底为输入；修改后其他各表自动更新。“来源”列注明出处，没有出处的标“占位假设”。
A4: 会员参数 | B4: 基础版 | C4: 标准版 | D4: 顾问版 | E4: 来源
A5: 月费(元) | B5: 199 | C5: 399 | D5: 1299 | E5: B01 V1.0 / BP V0.4
A6: 假设增量现金成本(元/家/月) | B6: 5 | C6: 10 | D6: 30 | E6: C02 V1.1 6.2（情景假设，非真实账单）
A7: 规模情景客户结构 | B7: 0.2 | C7: 0.7 | D7: 0.1 | E7: C02 V1.1 第九章（未验证）
A8: 乐观 | B8: 0.3 | C8: 0.8 | D8: 3 | E8: C02 V1.1 第十一章：稳定期每月人工小时（高度自动化）
A9: 基准 | B9: 0.6 | C9: 1.5 | D9: 5 | E9: C02 V1.1 第十一章：稳定期每月人工小时（部分人工）
A10: 压力 | B10: 1 | C10: 3 | D10: 8 | E10: C02 V1.1 第十一章：稳定期每月人工小时（人工需求偏高）
A11: 注：第8–10行为稳定期会员每月人工小时，不含首次建档与获客。
A13: 通用参数 | B13: 数值 | E13: 来源
A14: 当前效率情景 | B14: 基准 | E14: 下拉：乐观/基准/压力；影响所有工时测算
A15: 99元体验服务费(元/家) | B15: 99 | E15: D02 第八节
A16: 体验每家人工-低(小时/30天) | B16: 5.5 | E16: D01 7.2
A17: 体验每家人工-高(小时/30天) | B17: 12.5 | E17: D01 7.2
A18: 正式会员首次建档额外工时(小时/家) | B18: 3 | E18: C02 V1.1 第十三章示例
A19: 共享批量服务工时(小时/月) | B19: 12 | E19: C02 V1.1 第十一章
A20: 创始人月工作容量(小时) | B20: 132 | E20: C02 V1.1 第十二章：6小时×22天
A21: 客户服务预算(小时/月) | B21: 65 | E21: C02 V1.1 第十二章
A22: 常规排期参考线(小时/月) | B22: 52 | E22: BP 附录A / F02
A23: 固定现金预算(元/月) | B23: ='90天预算'!B15 | E23: 链接“90天预算”小计
A24: 基础版年费(元/年) | B24: 1980 | E24: B01 7.1
A27: 规模扩容费用 | B27: 客户规模(家) | C27: 扩容费用(元/月) | E27: 来源
A28: 情景A | B28: 20 | C28: 0 | E28: C02 V1.1 6.3（压力测算，非真实报价）
A29: 情景B | B29: 30 | C29: 600 | E29: C02 V1.1 6.3（压力测算，非真实报价）
A30: 情景C | B30: 50 | C30: 1500 | E30: C02 V1.1 6.3（压力测算，非真实报价）
A32: 高级专项（B08） | B32: 报价下限(元) | C32: 报价上限(元) | D32: 测算报价(元) | E32: 预计人工(小时) | F32: 外包/合作成本占比 | G32: 差旅等直接费用(元) | H32: 90天成交数(情景) | I32: 来源与说明
A33: P01 单一经营问题专项诊断 | B33: 3800 | C33: 8800 | D33: =AVERAGE(B33:C33) | E33: 26.5 | F33: 0 | G33: 200 | H33: 1 | I33: B08：报价、工时18–35小时（取中值）
A34: P02 经营改善行动专项 | B34: 9800 | C34: 29800 | D34: =AVERAGE(B34:C34) | E34: 60 | F34: 0.15 | G34: 300 | H34: 0 | I34: B08 报价；工时与外包占比为占位假设
A35: P03 新项目/扩张与复制决策 | B35: 12800 | C35: 39800 | D35: =AVERAGE(B35:C35) | E35: 45 | F35: 0.1 | G35: 300 | H35: 0 | I35: B08 报价；工时与外包占比为占位假设
A36: P04 AI与数字化经营改善 | B36: 8800 | C36: 39800 | D36: =AVERAGE(B36:C36) | E36: 50 | F36: 0.1 | G36: 200 | H36: 1 | I36: B08 报价；工时与外包占比为占位假设
A37: P05 外部经营顾问与陪跑（每月） | B37: 3000 | C37: 8000 | D37: =AVERAGE(B37:C37) | E37: 8 | F37: 0 | G37: 100 | H37: 0 | I37: B08：4–12小时/月取中值；按月计
A38: 会员专项简析 | B38: 2000 | C38: 5000 | D38: =AVERAGE(B38:C38) | E38: 10 | F38: 0 | G38: 0 | H38: 0 | I38: B01/B02 8.1；工时为占位假设
A39: “测算报价”默认取区间中值；可直接改为单一报价（覆盖公式）。报价均为内部测试区间，尚无真实成交。
A42: 90天会员线情景 | B42: 数值 | E42: 来源
A43: 90天体验企业数(家) | B43: 8 | E43: D01/F01：5–10家，分批2–3家
A44: 体验→正式会员转化率 | B44: 0.4 | E44: 占位假设；F01 目标“至少3家”
A45: 转正后在90天内平均付费月数 | B45: 1.5 | E45: 占位假设：分批启动，后批转正较晚
A47: 转正客户的档位结构沿用第7行“规模情景客户结构”。

Sheet 会员单客经济
A1: 会员单客户经济模型
A2: 现金口径（C02 V1.1）：创始人工时不计现金成本，单独作为产能约束。当前效率情景见“假设”B14。
A4: 指标 | B4: 基础版 | C4: 标准版 | D4: 顾问版 | E4: 说明
A5: 月费(元) | B5: =假设!B5 | C5: =假设!C5 | D5: =假设!D5
A6: 增量现金成本(元/月) | B6: =假设!B6 | C6: =假设!C6 | D6: =假设!D6 | E6: 已含在固定订阅内的用量不重复计
A7: 单位现金贡献(元/月) | B7: =B5-B6 | C7: =C5-C6 | D7: =D5-D6 | E7: 未扣固定预算、税费、获客与创始人薪酬；不是净利润
A8: 稳定期月人工(小时，当前情景) | B8: =INDEX(假设!B$8:B$10,MATCH(假设!$B$14,假设!$A$8:$A$10,0)) | C8: =INDEX(假设!C$8:C$10,MATCH(假设!$B$14,假设!$A$8:$A$10,0)) | D8: =INDEX(假设!D$8:D$10,MATCH(假设!$B$14,假设!$A$8:$A$10,0)) | E8: C02 第十一章
A9: 每人工小时现金贡献(元/时) | B9: =IF(B8=0,"",B7/B8) | C9: =IF(C8=0,"",C7/C8) | D9: =IF(D8=0,"",D7/D8) | E9: 与专项线比较的核心指标
A10: 覆盖固定预算所需客户数(仅此档) | B10: =IF(B7<=0,"",ROUNDUP(假设!$B$23/B7,0)) | C10: =IF(C7<=0,"",ROUNDUP(假设!$B$23/C7,0)) | D10: =IF(D7<=0,"",ROUNDUP(假设!$B$23/D7,0)) | E10: C02 第八章校验：应为 7 / 4 / 2
A11: 扣除共享工时后65小时可容纳客户数(仅此档) | B11: =IF(B8=0,"",ROUNDDOWN((假设!$B$21-假设!$B$19)/B8,0)) | C11: =IF(C8=0,"",ROUNDDOWN((假设!$B$21-假设!$B$19)/C8,0)) | D11: =IF(D8=0,"",ROUNDDOWN((假设!$B$21-假设!$B$19)/D8,0)) | E11: 未计新客建档与高峰响应，偏乐观
A12: 12个月现金贡献(元) | B12: =B7*12 | C12: =C7*12 | D12: =D7*12 | E12: 假设全年续费
A13: 首年人工(小时，含首次建档) | B13: =B8*12+假设!$B$18 | C13: =C8*12+假设!$B$18 | D13: =D8*12+假设!$B$18
A14: 首年每人工小时现金贡献(元/时) | B14: =IF(B13=0,"",B12/B13) | C14: =IF(C13=0,"",C12/C13) | D14: =IF(D13=0,"",D12/D13)
A17: 每人工小时现金贡献：三种效率情景对比（元/时）
A18: 情景 | B18: 基础版 | C18: 标准版 | D18: 顾问版
A19: 乐观 | B19: =IF(假设!B8=0,"",B$7/假设!B8) | C19: =IF(假设!C8=0,"",C$7/假设!C8) | D19: =IF(假设!D8=0,"",D$7/假设!D8)
A20: 基准 | B20: =IF(假设!B9=0,"",B$7/假设!B9) | C20: =IF(假设!C9=0,"",C$7/假设!C9) | D20: =IF(假设!D9=0,"",D$7/假设!D9)
A21: 压力 | B21: =IF(假设!B10=0,"",B$7/假设!B10) | C21: =IF(假设!C10=0,"",C$7/假设!C10) | D21: =IF(假设!D10=0,"",D$7/假设!D10)
A23: 99元30天体验（会员线入口）
A24: 指标 | B24: 低工时 | C24: 高工时 | E24: 说明
A25: 体验收入(元/家) | B25: =假设!$B$15 | C25: =假设!$B$15 | E25: 转正时全额抵扣首月会员费，不重复计收入
A26: 体验人工(小时/家) | B26: =假设!$B$16 | C26: =假设!$B$17 | E26: D01 7.2，不含获客
A27: 每人工小时现金(元/时) | B27: =IF(B26=0,"",B25/B26) | C27: =IF(C26=0,"",C25/C26) | E27: 体验期主要是获客与建档投入，不以此评价盈亏
A28: 转正为标准版后，收回体验工时所需月数 | B28: =IF($C$8=0,"",B26/$C$8) | C28: =IF($C$8=0,"",C26/$C$8) | E28: 体验工时 ÷ 标准版稳定期月工时：衡量体验期的“工时投资”相当于几个月的服务量

Sheet 规模情景
A1: 会员规模情景（稳定期）
A2: 复现并参数化 C02 V1.1 第九、十二章。不是第一年销售预测。
A4: 指标 | B4: 情景A | C4: 情景B | D4: 情景C | E4: 说明
A5: 会员规模(家) | B5: =假设!B28 | C5: =假设!B29 | D5: =假设!B30
A6: 基础版(家) | B6: =ROUND(B5*假设!$B$7,0) | C6: =ROUND(C5*假设!$B$7,0) | D6: =ROUND(D5*假设!$B$7,0) | E6: 按“假设”第7行结构
A7: 标准版(家) | B7: =ROUND(B5*假设!$C$7,0) | C7: =ROUND(C5*假设!$C$7,0) | D7: =ROUND(D5*假设!$C$7,0)
A8: 顾问版(家) | B8: =B5-B6-B7 | C8: =C5-C6-C7 | D8: =D5-D6-D7 | E8: 余数归顾问版，保证合计等于规模
A9: 会员收入 MRR(元/月) | B9: =B6*假设!$B$5+B7*假设!$C$5+B8*假设!$D$5 | C9: =C6*假设!$B$5+C7*假设!$C$5+C8*假设!$D$5 | D9: =D6*假设!$B$5+D7*假设!$C$5+D8*假设!$D$5 | E9: C02 校验：8980 / 13470 / 22450
A10: 增量现金成本(元/月) | B10: =B6*假设!$B$6+B7*假设!$C$6+B8*假设!$D$6 | C10: =C6*假设!$B$6+C7*假设!$C$6+C8*假设!$D$6 | D10: =D6*假设!$B$6+D7*假设!$C$6+D8*假设!$D$6
A11: 固定现金预算(元/月) | B11: =假设!$B$23 | C11: =假设!$B$23 | D11: =假设!$B$23
A12: 扩容费用(元/月) | B12: =假设!C28 | C12: =假设!C29 | D12: =假设!C30
A13: 月经营现金结余(元/月) | B13: =B9-B10-B11-B12 | C13: =C9-C10-C11-C12 | D13: =D9-D10-D11-D12 | E13: C02 校验：7462 / 11242 / 19102；未计税费、流失、获客、薪酬
A14: 稳定期服务工时-乐观(小时/月) | B14: =B6*假设!$B$8+B7*假设!$C$8+B8*假设!$D$8+假设!$B$19 | C14: =C6*假设!$B$8+C7*假设!$C$8+C8*假设!$D$8+假设!$B$19 | D14: =D6*假设!$B$8+D7*假设!$C$8+D8*假设!$D$8+假设!$B$19 | E14: 含共享12小时；C02 校验：30.4 / 39.6 / 58
A15: 稳定期服务工时-基准(小时/月) | B15: =B6*假设!$B$9+B7*假设!$C$9+B8*假设!$D$9+假设!$B$19 | C15: =C6*假设!$B$9+C7*假设!$C$9+C8*假设!$D$9+假设!$B$19 | D15: =D6*假设!$B$9+D7*假设!$C$9+D8*假设!$D$9+假设!$B$19 | E15: C02 校验：45.4 / 62.1 / 95.5
A16: 稳定期服务工时-压力(小时/月) | B16: =B6*假设!$B$10+B7*假设!$C$10+B8*假设!$D$10+假设!$B$19 | C16: =C6*假设!$B$10+C7*假设!$C$10+C8*假设!$D$10+假设!$B$19 | D16: =D6*假设!$B$10+D7*假设!$C$10+D8*假设!$D$10+假设!$B$19 | E16: C02 校验：74 / 105 / 167
A17: 当前情景工时(小时/月) | B17: =INDEX(B14:B16,MATCH(假设!$B$14,假设!$A$8:$A$10,0)) | C17: =INDEX(C14:C16,MATCH(假设!$B$14,假设!$A$8:$A$10,0)) | D17: =INDEX(D14:D16,MATCH(假设!$B$14,假设!$A$8:$A$10,0)) | E17: 按“假设”B14
A18: 占客户服务预算(65小时)比例 | B18: =IF(假设!$B$21=0,"",B17/假设!$B$21) | C18: =IF(假设!$B$21=0,"",C17/假设!$B$21) | D18: =IF(假设!$B$21=0,"",D17/假设!$B$21) | E18: >100% 即单人无法承接
A19: 是否超过常规排期参考线(52小时) | B19: =IF(B17>假设!$B$22,"超过","未超过") | C19: =IF(C17>假设!$B$22,"超过","未超过") | D19: =IF(D17>假设!$B$22,"超过","未超过") | E19: F02：不宜把排期填满65小时
A20: 当前情景每人工小时现金结余(元/时) | B20: =IF(B17=0,"",B13/B17) | C20: =IF(C17=0,"",C13/C17) | D20: =IF(D17=0,"",D13/D17)

Sheet 专项经济
A1: 高级专项单项目经济模型
A2: 按 B08 测试报价与假设工时。与会员线比较“每人工小时现金贡献”，用于 BP V0.4 17.7 主线裁决。
A4: 产品 | B4: 测算报价(元) | C4: 外包/合作成本(元) | D4: 差旅等直接费用(元) | E4: 项目现金贡献(元) | F4: 预计人工(小时) | G4: 每人工小时现金贡献(元/时) | H4: 相当于标准版几个月贡献 | I4: 65小时预算内每月最多可做(项)
A5: =假设!A33 | B5: =假设!D33 | C5: =B5*假设!F33 | D5: =假设!G33 | E5: =B5-C5-D5 | F5: =假设!E33 | G5: =IF(F5=0,"",E5/F5) | H5: =IF('会员单客经济'!$C$7=0,"",E5/'会员单客经济'!$C$7) | I5: =IF(F5=0,"",ROUNDDOWN(假设!$B$21/F5,1))
A6: =假设!A34 | B6: =假设!D34 | C6: =B6*假设!F34 | D6: =假设!G34 | E6: =B6-C6-D6 | F6: =假设!E34 | G6: =IF(F6=0,"",E6/F6) | H6: =IF('会员单客经济'!$C$7=0,"",E6/'会员单客经济'!$C$7) | I6: =IF(F6=0,"",ROUNDDOWN(假设!$B$21/F6,1))
A7: =假设!A35 | B7: =假设!D35 | C7: =B7*假设!F35 | D7: =假设!G35 | E7: =B7-C7-D7 | F7: =假设!E35 | G7: =IF(F7=0,"",E7/F7) | H7: =IF('会员单客经济'!$C$7=0,"",E7/'会员单客经济'!$C$7) | I7: =IF(F7=0,"",ROUNDDOWN(假设!$B$21/F7,1))
A8: =假设!A36 | B8: =假设!D36 | C8: =B8*假设!F36 | D8: =假设!G36 | E8: =B8-C8-D8 | F8: =假设!E36 | G8: =IF(F8=0,"",E8/F8) | H8: =IF('会员单客经济'!$C$7=0,"",E8/'会员单客经济'!$C$7) | I8: =IF(F8=0,"",ROUNDDOWN(假设!$B$21/F8,1))
A9: =假设!A37 | B9: =假设!D37 | C9: =B9*假设!F37 | D9: =假设!G37 | E9: =B9-C9-D9 | F9: =假设!E37 | G9: =IF(F9=0,"",E9/F9) | H9: =IF('会员单客经济'!$C$7=0,"",E9/'会员单客经济'!$C$7) | I9: =IF(F9=0,"",ROUNDDOWN(假设!$B$21/F9,1))
A10: =假设!A38 | B10: =假设!D38 | C10: =B10*假设!F38 | D10: =假设!G38 | E10: =B10-C10-D10 | F10: =假设!E38 | G10: =IF(F10=0,"",E10/F10) | H10: =IF('会员单客经济'!$C$7=0,"",E10/'会员单客经济'!$C$7) | I10: =IF(F10=0,"",ROUNDDOWN(假设!$B$21/F10,1))
A11: 对照：标准版399（当前情景） | G11: ='会员单客经济'!C9
A13: 说明：P01 约 18–35 小时/项（B08），P02–P04 的工时与外包占比在 B08 中没有给出，表中为占位假设，首单交付后用 D05 工时记录替换。P05 按月计。

Sheet 双线情景
A1: 90天双线情景（会员线 + 专项线）
A2: 情景推演，不是预测。输入在“假设”第43–45行与第33–38行H列。
A4: 指标 | B4: 会员线 | C4: 专项线 | D4: 合计 | E4: 说明
A5: 体验企业数 / 专项成交数 | B5: =假设!B43 | C5: =SUM(假设!$H$33:$H$38) | E5: 专项按“假设”H列各产品成交数
A6: 正式会员转正数(家) | B6: =ROUND(B5*假设!B44,0) | D6: =B6
A7: 体验收入(元) | B7: =B5*假设!B15 | D7: =B7 | E7: 99元/家
A8: 会员费收入(元) | B8: =B6*(假设!$B$7*假设!$B$5+假设!$C$7*假设!$C$5+假设!$D$7*假设!$D$5)*假设!B45-B6*假设!B15 | D8: =B8 | E8: 转正数×结构加权月费×付费月数，扣除已抵扣的99元
A9: 专项收入(元) | C9: =SUMPRODUCT(假设!$D$33:$D$38,假设!$H$33:$H$38) | D9: =C9 | E9: 测算报价×成交数；按全额到账计
A10: 90天收入合计(元) | B10: =B7+B8 | C10: =C9 | D10: =B10+C10
A11: 会员增量现金成本(元) | B11: =B6*(假设!$B$7*假设!$B$6+假设!$C$7*假设!$C$6+假设!$D$7*假设!$D$6)*假设!B45 | D11: =B11
A12: 专项外包与直接费用(元) | C12: =SUMPRODUCT(假设!$D$33:$D$38,假设!$F$33:$F$38,假设!$H$33:$H$38)+SUMPRODUCT(假设!$G$33:$G$38,假设!$H$33:$H$38) | D12: =C12
A13: 线上直接现金结余(元) | B13: =B10-B11 | C13: =C10-C12 | D13: =B13+C13 | E13: 未扣固定预算与一次性投入，见“90天预算”
A14: 体验期人工(小时) | B14: =B5*AVERAGE(假设!B16:B17) | D14: =B14 | E14: D01 区间中值
A15: 转正后稳定期人工(小时) | B15: =B6*(假设!$B$7*INDEX(假设!$B$8:$B$10,MATCH(假设!$B$14,假设!$A$8:$A$10,0))+假设!$C$7*INDEX(假设!$C$8:$C$10,MATCH(假设!$B$14,假设!$A$8:$A$10,0))+假设!$D$7*INDEX(假设!$D$8:$D$10,MATCH(假设!$B$14,假设!$A$8:$A$10,0)))*假设!B45 | D15: =B15 | E15: 当前效率情景
A16: 专项交付人工(小时) | C16: =SUMPRODUCT(假设!$E$33:$E$38,假设!$H$33:$H$38) | D16: =C16
A17: 共享批量服务(小时) | B17: =假设!B19*3 | D17: =B17 | E17: 记在会员线
A18: 90天客户服务人工合计(小时) | B18: =B14+B15+B17 | C18: =C16 | D18: =B18+C18 | E18: 不含获客、开发、协会
A19: 每人工小时直接现金结余(元/时) | B19: =IF(B18=0,"",B13/B18) | C19: =IF(C18=0,"",C13/C18) | D19: =IF(D18=0,"",D13/D18) | E19: 主线裁决比较项（BP V0.4 17.7）
A20: 90天客户服务预算(小时) | D20: =假设!B21*3 | E20: 65小时×3个月
A21: 客户服务预算占用率 | D21: =IF(D20=0,"",D18/D20) | E21: >100% 说明情景超出单人容量

Sheet 90天预算
A1: H01｜90天创业现金预算
A2: 重建自 C02 V1.1 / F02 / MVP 中散落的预算口径。原始明细文件《D03-A V1.2》缺失，仅“1298元/月”总额有文档出处。
A4: 项目 | B4: 月度金额(元) | C4: 90天合计(元) | D4: 依据 | E4: 状态
A5: 一、固定现金预算（每月）
A6: 大模型 API | B6: 200 | C6: =B6*3 | D6: MVP 第九章：约100–300元/月，取中值 | E6: 重建估计，待确认
A7: WorkBuddy | B7: 150 | C7: =B7*3 | D7: MVP 第九章：约100–200元/月，取中值 | E7: 重建估计，待确认
A8: 其他 AI 助手与工具软件订阅 | B8: 150 | C8: =B8*3 | D8: C02 2.1 列有“AI和软件订阅”，金额无出处 | E8: 重建估计，待确认
A9: 云存储与加密备份 | B9: 30 | C9: =B9*3 | D9: MVP 第九章：网盘0–30元/月，取上限 | E9: 重建估计，待确认
A10: 通信（业务手机号、流量） | B10: 100 | C10: =B10*3 | D10: C02 2.1 列有“通信”，金额无出处 | E10: 重建估计，待确认
A11: 客户拜访交通 | B11: 300 | C11: =B11*3 | D11: C02 2.1 列有“客户拜访交通”，金额无出处 | E11: 重建估计，待确认
A12: 推广及销售材料 | B12: 100 | C12: =B12*3 | D12: C02 2.1 列有“推广及销售材料”，金额无出处 | E12: 重建估计，待确认
A13: 记账及基本财税服务 | B13: 200 | C13: =B13*3 | D13: C02 2.1 列有“记账及基本财税服务”，金额无出处 | E13: 重建估计，待确认
A14: 银行及其他必要运营费用 | B14: 68 | C14: =B14*3 | D14: 平衡项：使合计等于文档口径1298元/月 | E14: 平衡项
A15: 固定现金预算小计 | B15: =SUM(B6:B14) | C15: =SUM(C6:C14) | D15: =IF(B15=1298,"✓ 与 C02/F02/BP 口径 1298元/月一致","⚠ 与文档口径 1298元/月不一致，请同步修订 C02/F02/BP")
A17: 二、一次性投入（90天内）
A18: 合同与数据授权文本法务审核 | C18: 2000 | D18: F01/D02 要求对外使用前完成法律审核；金额为占位假设 | E18: 占位假设，待询价
A19: 专用电脑 / 小主机 | C19: 0 | D19: MVP 第九章：0–5000元，可先用现有电脑 | E19: 按“先用现有电脑”
A20: 宣传折页与样例报告印刷 | C20: 300 | D20: 占位假设 | E20: 占位假设
A21: 经营主体注册、开户、开票准备 | C21: 0 | D21: B08 十一：签约主体须合规；如已有主体填0 | E21: 待确认
A22: 一次性投入小计 | C22: =SUM(C18:C21)
A24: 三、随业务发生的变动支出（来自“双线情景”）
A25: 会员增量现金成本 | C25: ='双线情景'!D11 | D25: 随“双线情景”变化 | E25: 情景推演
A26: 专项外包与直接费用 | C26: ='双线情景'!D12 | D26: 随“双线情景”变化 | E26: 情景推演
A27: 变动支出小计 | C27: =SUM(C25:C26)
A29: 四、90天现金汇总（情景）
A30: 90天现金支出合计(元) | C30: =C15+C22+C27 | D30: 固定×3 + 一次性 + 变动
A31: 90天收入(元，双线情景) | C31: ='双线情景'!D10 | D31: 见“双线情景”
A32: 90天项目现金结余(元) | C32: =C31-C30 | D32: F01 10.5 结果一口径；未计税费与创始人薪酬
A33: 盈亏平衡所需90天收入(元) | C33: =C30 | D33: 即覆盖全部现金支出
